{"version":3,"kind":"Notebook","sha256":"480ab8df1d27ccf7c5557ecb248536e0811cf4ec0f4e6a3b2e908f5c5a184401","slug":"perspective-1","location":"/notebooks/story/perspective_1.ipynb","dependencies":[],"frontmatter":{"title":"Strict lifestyle","content_includes_title":false,"kernelspec":{"name":"conda-base-py","display_name":"Python [conda env:base] *","language":"python"},"github":"https://github.com/ianv06/info-vis-5b","exports":[{"format":"ipynb","filename":"perspective_1.ipynb","url":"/perspective_1-eac2644b7ef6bbca60c001eaf4c6dd07.ipynb"}]},"widgets":{},"mdast":{"type":"root","children":[{"type":"block","kind":"notebook-content","data":{"editable":true,"slideshow":{"slide_type":""},"tags":[]},"children":[{"type":"paragraph","position":{"start":{"line":3,"column":1},"end":{"line":3,"column":1}},"children":[{"type":"emphasis","position":{"start":{"line":3,"column":1},"end":{"line":3,"column":1}},"children":[{"type":"text","value":"Having a strict lifestyle, such as focusing more on studying and reducing leisure activities, may improve students’ academic performance.","position":{"start":{"line":3,"column":1},"end":{"line":3,"column":1}},"key":"DQNi8jOBuN"}],"key":"nvswYJKmQy"}],"key":"eixl0RV5NM"}],"visibility":"show","key":"tomk7m7xZo"},{"type":"block","kind":"notebook-content","children":[{"type":"heading","depth":2,"position":{"start":{"line":1,"column":1},"end":{"line":1,"column":1}},"children":[{"type":"text","value":"Study time","position":{"start":{"line":1,"column":1},"end":{"line":1,"column":1}},"key":"ukgL298reL"}],"identifier":"study-time","label":"Study time","html_id":"study-time","implicit":true,"key":"TUBcEOzxYf"},{"type":"paragraph","position":{"start":{"line":3,"column":1},"end":{"line":3,"column":1}},"children":[{"type":"emphasis","position":{"start":{"line":3,"column":1},"end":{"line":3,"column":1}},"children":[{"type":"text","value":"Students spending more time studying tend to achieve higher academic performance.","position":{"start":{"line":3,"column":1},"end":{"line":3,"column":1}},"key":"y3pJRFbj2C"}],"key":"uObnGVbsVp"}],"key":"KAmZIBm0vN"}],"key":"VMW8cO6kxD"},{"type":"block","kind":"notebook-code","data":{"editable":true,"slideshow":{"slide_type":""},"tags":[]},"children":[{"type":"code","lang":"python","executable":true,"value":"%run ../plots/study_time_plot.ipynb","visibility":"remove","key":"ipbHefAZ9H"},{"type":"outputs","id":"28Nf3CGFOUNlVkIDZr7rH","children":[{"type":"output","jupyter_data":{"output_type":"display_data","metadata":{},"data":{"application/vnd.plotly.v1+json":{"content":"{\"config\":{\"plotlyServerURL\":\"https://plot.ly\"},\"data\":[{\"showlegend\":false,\"type\":\"bar\",\"x\":[\"Low\",\"Medium\",\"High\"],\"xaxis\":\"x\",\"y\":{\"bdata\":\"SyyJkxICGUBl8d5WSxYeQBFPtj+uTiFA\",\"dtype\":\"f8\"},\"yaxis\":\"y\"},{\"showlegend\":false,\"type\":\"bar\",\"x\":[\"Low\",\"Medium\",\"High\"],\"xaxis\":\"x2\",\"y\":{\"bdata\":\"dl6u1IXeCkCqtSo8j7IUQOmagZktvh5A\",\"dtype\":\"f8\"},\"yaxis\":\"y2\"},{\"name\":\"Math\",\"type\":\"bar\",\"x\":[\"Low\",\"Medium\",\"High\"],\"xaxis\":\"x3\",\"y\":{\"bdata\":\"ke5kPqQ7CUBptrF7jmYLQCIiIiIiIhBA\",\"dtype\":\"f8\"},\"yaxis\":\"y3\"},{\"name\":\"Portuguese\",\"type\":\"bar\",\"x\":[\"Low\",\"Medium\",\"High\"],\"xaxis\":\"x3\",\"y\":{\"bdata\":\"Ak+35odFAkAxSf8JdKcHQDfccMMNNw5A\",\"dtype\":\"f8\"},\"yaxis\":\"y3\"},{\"showlegend\":false,\"type\":\"bar\",\"x\":[\"Low\",\"Medium\",\"High\"],\"xaxis\":\"x4\",\"y\":{\"bdata\":\"++Sq/ylGBUB5YDDv4DURQHwKDHSpfxdA\",\"dtype\":\"f8\"},\"yaxis\":\"y4\"}],\"layout\":{\"annotations\":[{\"font\":{\"size\":16},\"showarrow\":false,\"text\":\"Student Lifestyle\",\"x\":0.22,\"xanchor\":\"center\",\"xref\":\"paper\",\"y\":1,\"yanchor\":\"bottom\",\"yref\":\"paper\"},{\"font\":{\"size\":16},\"showarrow\":false,\"text\":\"Gaming & Academic Performance\",\"x\":0.78,\"xanchor\":\"center\",\"xref\":\"paper\",\"y\":1,\"yanchor\":\"bottom\",\"yref\":\"paper\"},{\"font\":{\"size\":16},\"showarrow\":false,\"text\":\"Math vs Portuguese\",\"x\":0.22,\"xanchor\":\"center\",\"xref\":\"paper\",\"y\":0.41000000000000003,\"yanchor\":\"bottom\",\"yref\":\"paper\"},{\"font\":{\"size\":16},\"showarrow\":false,\"text\":\"Student Habits\",\"x\":0.78,\"xanchor\":\"center\",\"xref\":\"paper\",\"y\":0.41000000000000003,\"yanchor\":\"bottom\",\"yref\":\"paper\"}],\"bargap\":0.38,\"bargroupgap\":0.05,\"barmode\":\"group\",\"font\":{\"size\":9},\"height\":500,\"legend\":{\"title\":{\"text\":\"Subject\"}},\"margin\":{\"b\":35,\"l\":35,\"r\":15,\"t\":55},\"template\":{\"data\":{\"bar\":[{\"error_x\":{\"color\":\"#2a3f5f\"},\"error_y\":{\"color\":\"#2a3f5f\"},\"marker\":{\"line\":{\"color\":\"white\",\"width\":0.5},\"pattern\":{\"fillmode\":\"overlay\",\"size\":10,\"solidity\":0.2}},\"type\":\"bar\"}],\"barpolar\":[{\"marker\":{\"line\":{\"color\":\"white\",\"width\":0.5},\"pattern\":{\"fillmode\":\"overlay\",\"size\":10,\"solidity\":0.2}},\"type\":\"barpolar\"}],\"carpet\":[{\"aaxis\":{\"endlinecolor\":\"#2a3f5f\",\"gridcolor\":\"#C8D4E3\",\"linecolor\":\"#C8D4E3\",\"minorgridcolor\":\"#C8D4E3\",\"startlinecolor\":\"#2a3f5f\"},\"baxis\":{\"endlinecolor\":\"#2a3f5f\",\"gridcolor\":\"#C8D4E3\",\"linecolor\":\"#C8D4E3\",\"minorgridcolor\":\"#C8D4E3\",\"startlinecolor\":\"#2a3f5f\"},\"type\":\"carpet\"}],\"choropleth\":[{\"colorbar\":{\"outlinewidth\":0,\"ticks\":\"\"},\"type\":\"choropleth\"}],\"contour\":[{\"colorbar\":{\"outlinewidth\":0,\"ticks\":\"\"},\"colorscale\":[[0,\"#0d0887\"],[0.1111111111111111,\"#46039f\"],[0.2222222222222222,\"#7201a8\"],[0.3333333333333333,\"#9c179e\"],[0.4444444444444444,\"#bd3786\"],[0.5555555555555556,\"#d8576b\"],[0.6666666666666666,\"#ed7953\"],[0.7777777777777778,\"#fb9f3a\"],[0.8888888888888888,\"#fdca26\"],[1,\"#f0f921\"]],\"type\":\"contour\"}],\"contourcarpet\":[{\"colorbar\":{\"outlinewidth\":0,\"ticks\":\"\"},\"type\":\"contourcarpet\"}],\"heatmap\":[{\"colorbar\":{\"outlinewidth\":0,\"ticks\":\"\"},\"colorscale\":[[0,\"#0d0887\"],[0.1111111111111111,\"#46039f\"],[0.2222222222222222,\"#7201a8\"],[0.3333333333333333,\"#9c179e\"],[0.4444444444444444,\"#bd3786\"],[0.5555555555555556,\"#d8576b\"],[0.6666666666666666,\"#ed7953\"],[0.7777777777777778,\"#fb9f3a\"],[0.8888888888888888,\"#fdca26\"],[1,\"#f0f921\"]],\"type\":\"heatmap\"}],\"histogram\":[{\"marker\":{\"pattern\":{\"fillmode\":\"overlay\",\"size\":10,\"solidity\":0.2}},\"type\":\"histogram\"}],\"histogram2d\":[{\"colorbar\":{\"outlinewidth\":0,\"ticks\":\"\"},\"colorscale\":[[0,\"#0d0887\"],[0.1111111111111111,\"#46039f\"],[0.2222222222222222,\"#7201a8\"],[0.3333333333333333,\"#9c179e\"],[0.4444444444444444,\"#bd3786\"],[0.5555555555555556,\"#d8576b\"],[0.6666666666666666,\"#ed7953\"],[0.7777777777777778,\"#fb9f3a\"],[0.8888888888888888,\"#fdca26\"],[1,\"#f0f921\"]],\"type\":\"histogram2d\"}],\"histogram2dcontour\":[{\"colorbar\":{\"outlinewidth\":0,\"ticks\":\"\"},\"colorscale\":[[0,\"#0d0887\"],[0.1111111111111111,\"#46039f\"],[0.2222222222222222,\"#7201a8\"],[0.3333333333333333,\"#9c179e\"],[0.4444444444444444,\"#bd3786\"],[0.5555555555555556,\"#d8576b\"],[0.6666666666666666,\"#ed7953\"],[0.7777777777777778,\"#fb9f3a\"],[0.8888888888888888,\"#fdca26\"],[1,\"#f0f921\"]],\"type\":\"histogram2dcontour\"}],\"mesh3d\":[{\"colorbar\":{\"outlinewidth\":0,\"ticks\":\"\"},\"type\":\"mesh3d\"}],\"parcoords\":[{\"line\":{\"colorbar\":{\"outlinewidth\":0,\"ticks\":\"\"}},\"type\":\"parcoords\"}],\"pie\":[{\"automargin\":true,\"type\":\"pie\"}],\"scatter\":[{\"fillpattern\":{\"fillmode\":\"overlay\",\"size\":10,\"solidity\":0.2},\"type\":\"scatter\"}],\"scatter3d\":[{\"line\":{\"colorbar\":{\"outlinewidth\":0,\"ticks\":\"\"}},\"marker\":{\"colorbar\":{\"outlinewidth\":0,\"ticks\":\"\"}},\"type\":\"scatter3d\"}],\"scattercarpet\":[{\"marker\":{\"colorbar\":{\"outlinewidth\":0,\"ticks\":\"\"}},\"type\":\"scattercarpet\"}],\"scattergeo\":[{\"marker\":{\"colorbar\":{\"outlinewidth\":0,\"ticks\":\"\"}},\"type\":\"scattergeo\"}],\"scattergl\":[{\"marker\":{\"colorbar\":{\"outlinewidth\":0,\"ticks\":\"\"}},\"type\":\"scattergl\"}],\"scattermap\":[{\"marker\":{\"colorbar\":{\"outlinewidth\":0,\"ticks\":\"\"}},\"type\":\"scattermap\"}],\"scattermapbox\":[{\"marker\":{\"colorbar\":{\"outlinewidth\":0,\"ticks\":\"\"}},\"type\":\"scattermapbox\"}],\"scatterpolar\":[{\"marker\":{\"colorbar\":{\"outlinewidth\":0,\"ticks\":\"\"}},\"type\":\"scatterpolar\"}],\"scatterpolargl\":[{\"marker\":{\"colorbar\":{\"outlinewidth\":0,\"ticks\":\"\"}},\"type\":\"scatterpolargl\"}],\"scatterternary\":[{\"marker\":{\"colorbar\":{\"outlinewidth\":0,\"ticks\":\"\"}},\"type\":\"scatterternary\"}],\"surface\":[{\"colorbar\":{\"outlinewidth\":0,\"ticks\":\"\"},\"colorscale\":[[0,\"#0d0887\"],[0.1111111111111111,\"#46039f\"],[0.2222222222222222,\"#7201a8\"],[0.3333333333333333,\"#9c179e\"],[0.4444444444444444,\"#bd3786\"],[0.5555555555555556,\"#d8576b\"],[0.6666666666666666,\"#ed7953\"],[0.7777777777777778,\"#fb9f3a\"],[0.8888888888888888,\"#fdca26\"],[1,\"#f0f921\"]],\"type\":\"surface\"}],\"table\":[{\"cells\":{\"fill\":{\"color\":\"#EBF0F8\"},\"line\":{\"color\":\"white\"}},\"header\":{\"fill\":{\"color\":\"#C8D4E3\"},\"line\":{\"color\":\"white\"}},\"type\":\"table\"}]},\"layout\":{\"annotationdefaults\":{\"arrowcolor\":\"#2a3f5f\",\"arrowhead\":0,\"arrowwidth\":1},\"autotypenumbers\":\"strict\",\"coloraxis\":{\"colorbar\":{\"outlinewidth\":0,\"ticks\":\"\"}},\"colorscale\":{\"diverging\":[[0,\"#8e0152\"],[0.1,\"#c51b7d\"],[0.2,\"#de77ae\"],[0.3,\"#f1b6da\"],[0.4,\"#fde0ef\"],[0.5,\"#f7f7f7\"],[0.6,\"#e6f5d0\"],[0.7,\"#b8e186\"],[0.8,\"#7fbc41\"],[0.9,\"#4d9221\"],[1,\"#276419\"]],\"sequential\":[[0,\"#0d0887\"],[0.1111111111111111,\"#46039f\"],[0.2222222222222222,\"#7201a8\"],[0.3333333333333333,\"#9c179e\"],[0.4444444444444444,\"#bd3786\"],[0.5555555555555556,\"#d8576b\"],[0.6666666666666666,\"#ed7953\"],[0.7777777777777778,\"#fb9f3a\"],[0.8888888888888888,\"#fdca26\"],[1,\"#f0f921\"]],\"sequentialminus\":[[0,\"#0d0887\"],[0.1111111111111111,\"#46039f\"],[0.2222222222222222,\"#7201a8\"],[0.3333333333333333,\"#9c179e\"],[0.4444444444444444,\"#bd3786\"],[0.5555555555555556,\"#d8576b\"],[0.6666666666666666,\"#ed7953\"],[0.7777777777777778,\"#fb9f3a\"],[0.8888888888888888,\"#fdca26\"],[1,\"#f0f921\"]]},\"colorway\":[\"#636efa\",\"#EF553B\",\"#00cc96\",\"#ab63fa\",\"#FFA15A\",\"#19d3f3\",\"#FF6692\",\"#B6E880\",\"#FF97FF\",\"#FECB52\"],\"font\":{\"color\":\"#2a3f5f\"},\"geo\":{\"bgcolor\":\"white\",\"lakecolor\":\"white\",\"landcolor\":\"white\",\"showlakes\":true,\"showland\":true,\"subunitcolor\":\"#C8D4E3\"},\"hoverlabel\":{\"align\":\"left\"},\"hovermode\":\"closest\",\"mapbox\":{\"style\":\"light\"},\"paper_bgcolor\":\"white\",\"plot_bgcolor\":\"white\",\"polar\":{\"angularaxis\":{\"gridcolor\":\"#EBF0F8\",\"linecolor\":\"#EBF0F8\",\"ticks\":\"\"},\"bgcolor\":\"white\",\"radialaxis\":{\"gridcolor\":\"#EBF0F8\",\"linecolor\":\"#EBF0F8\",\"ticks\":\"\"}},\"scene\":{\"xaxis\":{\"backgroundcolor\":\"white\",\"gridcolor\":\"#DFE8F3\",\"gridwidth\":2,\"linecolor\":\"#EBF0F8\",\"showbackground\":true,\"ticks\":\"\",\"zerolinecolor\":\"#EBF0F8\"},\"yaxis\":{\"backgroundcolor\":\"white\",\"gridcolor\":\"#DFE8F3\",\"gridwidth\":2,\"linecolor\":\"#EBF0F8\",\"showbackground\":true,\"ticks\":\"\",\"zerolinecolor\":\"#EBF0F8\"},\"zaxis\":{\"backgroundcolor\":\"white\",\"gridcolor\":\"#DFE8F3\",\"gridwidth\":2,\"linecolor\":\"#EBF0F8\",\"showbackground\":true,\"ticks\":\"\",\"zerolinecolor\":\"#EBF0F8\"}},\"shapedefaults\":{\"line\":{\"color\":\"#2a3f5f\"}},\"ternary\":{\"aaxis\":{\"gridcolor\":\"#DFE8F3\",\"linecolor\":\"#A2B1C6\",\"ticks\":\"\"},\"baxis\":{\"gridcolor\":\"#DFE8F3\",\"linecolor\":\"#A2B1C6\",\"ticks\":\"\"},\"bgcolor\":\"white\",\"caxis\":{\"gridcolor\":\"#DFE8F3\",\"linecolor\":\"#A2B1C6\",\"ticks\":\"\"}},\"title\":{\"x\":0.05},\"xaxis\":{\"automargin\":true,\"gridcolor\":\"#EBF0F8\",\"linecolor\":\"#EBF0F8\",\"ticks\":\"\",\"title\":{\"standoff\":15},\"zerolinecolor\":\"#EBF0F8\",\"zerolinewidth\":2},\"yaxis\":{\"automargin\":true,\"gridcolor\":\"#EBF0F8\",\"linecolor\":\"#EBF0F8\",\"ticks\":\"\",\"title\":{\"standoff\":15},\"zerolinecolor\":\"#EBF0F8\",\"zerolinewidth\":2}}},\"title\":{\"font\":{\"size\":13}},\"width\":700,\"xaxis\":{\"anchor\":\"y\",\"domain\":[0,0.44],\"tickfont\":{\"size\":8},\"title\":{\"font\":{\"size\":10},\"text\":\"Grade Group\"}},\"xaxis2\":{\"anchor\":\"y2\",\"domain\":[0.56,1],\"tickfont\":{\"size\":8},\"title\":{\"font\":{\"size\":10},\"text\":\"Grade Group\"}},\"xaxis3\":{\"anchor\":\"y3\",\"domain\":[0,0.44],\"tickfont\":{\"size\":8},\"title\":{\"font\":{\"size\":10},\"text\":\"Grade Group\"}},\"xaxis4\":{\"anchor\":\"y4\",\"domain\":[0.56,1],\"tickfont\":{\"size\":8},\"title\":{\"font\":{\"size\":10},\"text\":\"Grade Group\"}},\"yaxis\":{\"anchor\":\"x\",\"domain\":[0.5900000000000001,1],\"range\":[0,10],\"tickfont\":{\"size\":8},\"title\":{\"font\":{\"size\":10},\"text\":\"Average Study Time Score (0–10)\"}},\"yaxis2\":{\"anchor\":\"x2\",\"domain\":[0.5900000000000001,1],\"range\":[0,10],\"tickfont\":{\"size\":8},\"title\":{\"font\":{\"size\":10},\"text\":\"Average Study Time Score (0–10)\"}},\"yaxis3\":{\"anchor\":\"x3\",\"domain\":[0,0.41000000000000003],\"range\":[0,10],\"tickfont\":{\"size\":8},\"title\":{\"font\":{\"size\":10},\"text\":\"Average Study Time Score (0–10)\"}},\"yaxis4\":{\"anchor\":\"x4\",\"domain\":[0,0.41000000000000003],\"range\":[0,10],\"tickfont\":{\"size\":8},\"title\":{\"font\":{\"size\":10},\"text\":\"Average Study Time Score (0–10)\"}}}}","content_type":"application/vnd.plotly.v1+json"},"image/png":{"content_type":"image/png","hash":"59b757dd5a900b31b08a774bab9937f3","path":"/59b757dd5a900b31b08a774bab9937f3.png"},"text/html":{"content":"<div>            <script src=\"https://cdnjs.cloudflare.com/ajax/libs/mathjax/2.7.5/MathJax.js?config=TeX-AMS-MML_SVG\"></script><script>if (window.MathJax && window.MathJax.Hub && window.MathJax.Hub.Config) {window.MathJax.Hub.Config({SVG: {font: \"STIX-Web\"}});}</script>                <script>window.PlotlyConfig = {MathJaxConfig: 'local'};</script>\n        <script charset=\"utf-8\" src=\"https://cdn.plot.ly/plotly-3.5.0.min.js\" integrity=\"sha256-fHbNLP+GlIXN+efbQec78UkemUz3NJp7UmfGxC1tNxs=\" crossorigin=\"anonymous\"></script>                <div id=\"24700587-2000-4ab0-bd40-3911b494a9a7\" class=\"plotly-graph-div\" style=\"height:500px; width:700px;\"></div>            <script>                window.PLOTLYENV=window.PLOTLYENV || {};                                if (document.getElementById(\"24700587-2000-4ab0-bd40-3911b494a9a7\")) {                    Plotly.newPlot(                        \"24700587-2000-4ab0-bd40-3911b494a9a7\",                        [{\"showlegend\":false,\"x\":[\"Low\",\"Medium\",\"High\"],\"y\":{\"dtype\":\"f8\",\"bdata\":\"SyyJkxICGUBl8d5WSxYeQBFPtj+uTiFA\"},\"type\":\"bar\",\"xaxis\":\"x\",\"yaxis\":\"y\"},{\"showlegend\":false,\"x\":[\"Low\",\"Medium\",\"High\"],\"y\":{\"dtype\":\"f8\",\"bdata\":\"dl6u1IXeCkCqtSo8j7IUQOmagZktvh5A\"},\"type\":\"bar\",\"xaxis\":\"x2\",\"yaxis\":\"y2\"},{\"name\":\"Math\",\"x\":[\"Low\",\"Medium\",\"High\"],\"y\":{\"dtype\":\"f8\",\"bdata\":\"ke5kPqQ7CUBptrF7jmYLQCIiIiIiIhBA\"},\"type\":\"bar\",\"xaxis\":\"x3\",\"yaxis\":\"y3\"},{\"name\":\"Portuguese\",\"x\":[\"Low\",\"Medium\",\"High\"],\"y\":{\"dtype\":\"f8\",\"bdata\":\"Ak+35odFAkAxSf8JdKcHQDfccMMNNw5A\"},\"type\":\"bar\",\"xaxis\":\"x3\",\"yaxis\":\"y3\"},{\"showlegend\":false,\"x\":[\"Low\",\"Medium\",\"High\"],\"y\":{\"dtype\":\"f8\",\"bdata\":\"++Sq\\u002fylGBUB5YDDv4DURQHwKDHSpfxdA\"},\"type\":\"bar\",\"xaxis\":\"x4\",\"yaxis\":\"y4\"}],                        {\"template\":{\"data\":{\"barpolar\":[{\"marker\":{\"line\":{\"color\":\"white\",\"width\":0.5},\"pattern\":{\"fillmode\":\"overlay\",\"size\":10,\"solidity\":0.2}},\"type\":\"barpolar\"}],\"bar\":[{\"error_x\":{\"color\":\"#2a3f5f\"},\"error_y\":{\"color\":\"#2a3f5f\"},\"marker\":{\"line\":{\"color\":\"white\",\"width\":0.5},\"pattern\":{\"fillmode\":\"overlay\",\"size\":10,\"solidity\":0.2}},\"type\":\"bar\"}],\"carpet\":[{\"aaxis\":{\"endlinecolor\":\"#2a3f5f\",\"gridcolor\":\"#C8D4E3\",\"linecolor\":\"#C8D4E3\",\"minorgridcolor\":\"#C8D4E3\",\"startlinecolor\":\"#2a3f5f\"},\"baxis\":{\"endlinecolor\":\"#2a3f5f\",\"gridcolor\":\"#C8D4E3\",\"linecolor\":\"#C8D4E3\",\"minorgridcolor\":\"#C8D4E3\",\"startlinecolor\":\"#2a3f5f\"},\"type\":\"carpet\"}],\"choropleth\":[{\"colorbar\":{\"outlinewidth\":0,\"ticks\":\"\"},\"type\":\"choropleth\"}],\"contourcarpet\":[{\"colorbar\":{\"outlinewidth\":0,\"ticks\":\"\"},\"type\":\"contourcarpet\"}],\"contour\":[{\"colorbar\":{\"outlinewidth\":0,\"ticks\":\"\"},\"colorscale\":[[0.0,\"#0d0887\"],[0.1111111111111111,\"#46039f\"],[0.2222222222222222,\"#7201a8\"],[0.3333333333333333,\"#9c179e\"],[0.4444444444444444,\"#bd3786\"],[0.5555555555555556,\"#d8576b\"],[0.6666666666666666,\"#ed7953\"],[0.7777777777777778,\"#fb9f3a\"],[0.8888888888888888,\"#fdca26\"],[1.0,\"#f0f921\"]],\"type\":\"contour\"}],\"heatmap\":[{\"colorbar\":{\"outlinewidth\":0,\"ticks\":\"\"},\"colorscale\":[[0.0,\"#0d0887\"],[0.1111111111111111,\"#46039f\"],[0.2222222222222222,\"#7201a8\"],[0.3333333333333333,\"#9c179e\"],[0.4444444444444444,\"#bd3786\"],[0.5555555555555556,\"#d8576b\"],[0.6666666666666666,\"#ed7953\"],[0.7777777777777778,\"#fb9f3a\"],[0.8888888888888888,\"#fdca26\"],[1.0,\"#f0f921\"]],\"type\":\"heatmap\"}],\"histogram2dcontour\":[{\"colorbar\":{\"outlinewidth\":0,\"ticks\":\"\"},\"colorscale\":[[0.0,\"#0d0887\"],[0.1111111111111111,\"#46039f\"],[0.2222222222222222,\"#7201a8\"],[0.3333333333333333,\"#9c179e\"],[0.4444444444444444,\"#bd3786\"],[0.5555555555555556,\"#d8576b\"],[0.6666666666666666,\"#ed7953\"],[0.7777777777777778,\"#fb9f3a\"],[0.8888888888888888,\"#fdca26\"],[1.0,\"#f0f921\"]],\"type\":\"histogram2dcontour\"}],\"histogram2d\":[{\"colorbar\":{\"outlinewidth\":0,\"ticks\":\"\"},\"colorscale\":[[0.0,\"#0d0887\"],[0.1111111111111111,\"#46039f\"],[0.2222222222222222,\"#7201a8\"],[0.3333333333333333,\"#9c179e\"],[0.4444444444444444,\"#bd3786\"],[0.5555555555555556,\"#d8576b\"],[0.6666666666666666,\"#ed7953\"],[0.7777777777777778,\"#fb9f3a\"],[0.8888888888888888,\"#fdca26\"],[1.0,\"#f0f921\"]],\"type\":\"histogram2d\"}],\"histogram\":[{\"marker\":{\"pattern\":{\"fillmode\":\"overlay\",\"size\":10,\"solidity\":0.2}},\"type\":\"histogram\"}],\"mesh3d\":[{\"colorbar\":{\"outlinewidth\":0,\"ticks\":\"\"},\"type\":\"mesh3d\"}],\"parcoords\":[{\"line\":{\"colorbar\":{\"outlinewidth\":0,\"ticks\":\"\"}},\"type\":\"parcoords\"}],\"pie\":[{\"automargin\":true,\"type\":\"pie\"}],\"scatter3d\":[{\"line\":{\"colorbar\":{\"outlinewidth\":0,\"ticks\":\"\"}},\"marker\":{\"colorbar\":{\"outlinewidth\":0,\"ticks\":\"\"}},\"type\":\"scatter3d\"}],\"scattercarpet\":[{\"marker\":{\"colorbar\":{\"outlinewidth\":0,\"ticks\":\"\"}},\"type\":\"scattercarpet\"}],\"scattergeo\":[{\"marker\":{\"colorbar\":{\"outlinewidth\":0,\"ticks\":\"\"}},\"type\":\"scattergeo\"}],\"scattergl\":[{\"marker\":{\"colorbar\":{\"outlinewidth\":0,\"ticks\":\"\"}},\"type\":\"scattergl\"}],\"scattermapbox\":[{\"marker\":{\"colorbar\":{\"outlinewidth\":0,\"ticks\":\"\"}},\"type\":\"scattermapbox\"}],\"scattermap\":[{\"marker\":{\"colorbar\":{\"outlinewidth\":0,\"ticks\":\"\"}},\"type\":\"scattermap\"}],\"scatterpolargl\":[{\"marker\":{\"colorbar\":{\"outlinewidth\":0,\"ticks\":\"\"}},\"type\":\"scatterpolargl\"}],\"scatterpolar\":[{\"marker\":{\"colorbar\":{\"outlinewidth\":0,\"ticks\":\"\"}},\"type\":\"scatterpolar\"}],\"scatter\":[{\"fillpattern\":{\"fillmode\":\"overlay\",\"size\":10,\"solidity\":0.2},\"type\":\"scatter\"}],\"scatterternary\":[{\"marker\":{\"colorbar\":{\"outlinewidth\":0,\"ticks\":\"\"}},\"type\":\"scatterternary\"}],\"surface\":[{\"colorbar\":{\"outlinewidth\":0,\"ticks\":\"\"},\"colorscale\":[[0.0,\"#0d0887\"],[0.1111111111111111,\"#46039f\"],[0.2222222222222222,\"#7201a8\"],[0.3333333333333333,\"#9c179e\"],[0.4444444444444444,\"#bd3786\"],[0.5555555555555556,\"#d8576b\"],[0.6666666666666666,\"#ed7953\"],[0.7777777777777778,\"#fb9f3a\"],[0.8888888888888888,\"#fdca26\"],[1.0,\"#f0f921\"]],\"type\":\"surface\"}],\"table\":[{\"cells\":{\"fill\":{\"color\":\"#EBF0F8\"},\"line\":{\"color\":\"white\"}},\"header\":{\"fill\":{\"color\":\"#C8D4E3\"},\"line\":{\"color\":\"white\"}},\"type\":\"table\"}]},\"layout\":{\"annotationdefaults\":{\"arrowcolor\":\"#2a3f5f\",\"arrowhead\":0,\"arrowwidth\":1},\"autotypenumbers\":\"strict\",\"coloraxis\":{\"colorbar\":{\"outlinewidth\":0,\"ticks\":\"\"}},\"colorscale\":{\"diverging\":[[0,\"#8e0152\"],[0.1,\"#c51b7d\"],[0.2,\"#de77ae\"],[0.3,\"#f1b6da\"],[0.4,\"#fde0ef\"],[0.5,\"#f7f7f7\"],[0.6,\"#e6f5d0\"],[0.7,\"#b8e186\"],[0.8,\"#7fbc41\"],[0.9,\"#4d9221\"],[1,\"#276419\"]],\"sequential\":[[0.0,\"#0d0887\"],[0.1111111111111111,\"#46039f\"],[0.2222222222222222,\"#7201a8\"],[0.3333333333333333,\"#9c179e\"],[0.4444444444444444,\"#bd3786\"],[0.5555555555555556,\"#d8576b\"],[0.6666666666666666,\"#ed7953\"],[0.7777777777777778,\"#fb9f3a\"],[0.8888888888888888,\"#fdca26\"],[1.0,\"#f0f921\"]],\"sequentialminus\":[[0.0,\"#0d0887\"],[0.1111111111111111,\"#46039f\"],[0.2222222222222222,\"#7201a8\"],[0.3333333333333333,\"#9c179e\"],[0.4444444444444444,\"#bd3786\"],[0.5555555555555556,\"#d8576b\"],[0.6666666666666666,\"#ed7953\"],[0.7777777777777778,\"#fb9f3a\"],[0.8888888888888888,\"#fdca26\"],[1.0,\"#f0f921\"]]},\"colorway\":[\"#636efa\",\"#EF553B\",\"#00cc96\",\"#ab63fa\",\"#FFA15A\",\"#19d3f3\",\"#FF6692\",\"#B6E880\",\"#FF97FF\",\"#FECB52\"],\"font\":{\"color\":\"#2a3f5f\"},\"geo\":{\"bgcolor\":\"white\",\"lakecolor\":\"white\",\"landcolor\":\"white\",\"showlakes\":true,\"showland\":true,\"subunitcolor\":\"#C8D4E3\"},\"hoverlabel\":{\"align\":\"left\"},\"hovermode\":\"closest\",\"mapbox\":{\"style\":\"light\"},\"paper_bgcolor\":\"white\",\"plot_bgcolor\":\"white\",\"polar\":{\"angularaxis\":{\"gridcolor\":\"#EBF0F8\",\"linecolor\":\"#EBF0F8\",\"ticks\":\"\"},\"bgcolor\":\"white\",\"radialaxis\":{\"gridcolor\":\"#EBF0F8\",\"linecolor\":\"#EBF0F8\",\"ticks\":\"\"}},\"scene\":{\"xaxis\":{\"backgroundcolor\":\"white\",\"gridcolor\":\"#DFE8F3\",\"gridwidth\":2,\"linecolor\":\"#EBF0F8\",\"showbackground\":true,\"ticks\":\"\",\"zerolinecolor\":\"#EBF0F8\"},\"yaxis\":{\"backgroundcolor\":\"white\",\"gridcolor\":\"#DFE8F3\",\"gridwidth\":2,\"linecolor\":\"#EBF0F8\",\"showbackground\":true,\"ticks\":\"\",\"zerolinecolor\":\"#EBF0F8\"},\"zaxis\":{\"backgroundcolor\":\"white\",\"gridcolor\":\"#DFE8F3\",\"gridwidth\":2,\"linecolor\":\"#EBF0F8\",\"showbackground\":true,\"ticks\":\"\",\"zerolinecolor\":\"#EBF0F8\"}},\"shapedefaults\":{\"line\":{\"color\":\"#2a3f5f\"}},\"ternary\":{\"aaxis\":{\"gridcolor\":\"#DFE8F3\",\"linecolor\":\"#A2B1C6\",\"ticks\":\"\"},\"baxis\":{\"gridcolor\":\"#DFE8F3\",\"linecolor\":\"#A2B1C6\",\"ticks\":\"\"},\"bgcolor\":\"white\",\"caxis\":{\"gridcolor\":\"#DFE8F3\",\"linecolor\":\"#A2B1C6\",\"ticks\":\"\"}},\"title\":{\"x\":0.05},\"xaxis\":{\"automargin\":true,\"gridcolor\":\"#EBF0F8\",\"linecolor\":\"#EBF0F8\",\"ticks\":\"\",\"title\":{\"standoff\":15},\"zerolinecolor\":\"#EBF0F8\",\"zerolinewidth\":2},\"yaxis\":{\"automargin\":true,\"gridcolor\":\"#EBF0F8\",\"linecolor\":\"#EBF0F8\",\"ticks\":\"\",\"title\":{\"standoff\":15},\"zerolinecolor\":\"#EBF0F8\",\"zerolinewidth\":2}}},\"xaxis\":{\"anchor\":\"y\",\"domain\":[0.0,0.44],\"title\":{\"font\":{\"size\":10},\"text\":\"Grade Group\"},\"tickfont\":{\"size\":8}},\"yaxis\":{\"anchor\":\"x\",\"domain\":[0.5900000000000001,1.0],\"title\":{\"font\":{\"size\":10},\"text\":\"Average Study Time Score (0\\u201310)\"},\"tickfont\":{\"size\":8},\"range\":[0,10]},\"xaxis2\":{\"anchor\":\"y2\",\"domain\":[0.56,1.0],\"title\":{\"font\":{\"size\":10},\"text\":\"Grade Group\"},\"tickfont\":{\"size\":8}},\"yaxis2\":{\"anchor\":\"x2\",\"domain\":[0.5900000000000001,1.0],\"title\":{\"font\":{\"size\":10},\"text\":\"Average Study Time Score (0\\u201310)\"},\"tickfont\":{\"size\":8},\"range\":[0,10]},\"xaxis3\":{\"anchor\":\"y3\",\"domain\":[0.0,0.44],\"title\":{\"font\":{\"size\":10},\"text\":\"Grade Group\"},\"tickfont\":{\"size\":8}},\"yaxis3\":{\"anchor\":\"x3\",\"domain\":[0.0,0.41000000000000003],\"title\":{\"font\":{\"size\":10},\"text\":\"Average Study Time Score (0\\u201310)\"},\"tickfont\":{\"size\":8},\"range\":[0,10]},\"xaxis4\":{\"anchor\":\"y4\",\"domain\":[0.56,1.0],\"title\":{\"font\":{\"size\":10},\"text\":\"Grade Group\"},\"tickfont\":{\"size\":8}},\"yaxis4\":{\"anchor\":\"x4\",\"domain\":[0.0,0.41000000000000003],\"title\":{\"font\":{\"size\":10},\"text\":\"Average Study Time Score (0\\u201310)\"},\"tickfont\":{\"size\":8},\"range\":[0,10]},\"annotations\":[{\"font\":{\"size\":16},\"showarrow\":false,\"text\":\"Student Lifestyle\",\"x\":0.22,\"xanchor\":\"center\",\"xref\":\"paper\",\"y\":1.0,\"yanchor\":\"bottom\",\"yref\":\"paper\"},{\"font\":{\"size\":16},\"showarrow\":false,\"text\":\"Gaming & Academic Performance\",\"x\":0.78,\"xanchor\":\"center\",\"xref\":\"paper\",\"y\":1.0,\"yanchor\":\"bottom\",\"yref\":\"paper\"},{\"font\":{\"size\":16},\"showarrow\":false,\"text\":\"Math vs Portuguese\",\"x\":0.22,\"xanchor\":\"center\",\"xref\":\"paper\",\"y\":0.41000000000000003,\"yanchor\":\"bottom\",\"yref\":\"paper\"},{\"font\":{\"size\":16},\"showarrow\":false,\"text\":\"Student Habits\",\"x\":0.78,\"xanchor\":\"center\",\"xref\":\"paper\",\"y\":0.41000000000000003,\"yanchor\":\"bottom\",\"yref\":\"paper\"}],\"legend\":{\"title\":{\"text\":\"Subject\"}},\"margin\":{\"l\":35,\"r\":15,\"t\":55,\"b\":35},\"font\":{\"size\":9},\"title\":{\"font\":{\"size\":13}},\"barmode\":\"group\",\"height\":500,\"width\":700,\"bargap\":0.38,\"bargroupgap\":0.05},                        {\"responsive\": true}                    ).then(function(){\n                            \nvar gd = document.getElementById('24700587-2000-4ab0-bd40-3911b494a9a7');\nvar x = new MutationObserver(function (mutations, observer) {{\n        var display = window.getComputedStyle(gd).display;\n        if (!display || display === 'none') {{\n            console.log([gd, 'removed!']);\n            Plotly.purge(gd);\n            observer.disconnect();\n        }}\n}});\n\n// Listen for the removal of the full notebook cells\nvar notebookContainer = gd.closest('#notebook-container');\nif (notebookContainer) {{\n    x.observe(notebookContainer, {childList: true});\n}}\n\n// Listen for the clearing of the current output cell\nvar outputEl = gd.closest('.output');\nif (outputEl) {{\n    x.observe(outputEl, {childList: true});\n}}\n\n                        })                };            </script>        </div>","content_type":"text/html"}}},"children":[],"key":"giT3p9wwjz"}],"visibility":"show","key":"jd4Rvkq9EF"}],"class":"col-page-right","visibility":"show","key":"iJ5wK20fPv"},{"type":"block","kind":"notebook-content","children":[{"type":"paragraph","position":{"start":{"line":1,"column":1},"end":{"line":1,"column":1}},"children":[{"type":"emphasis","position":{"start":{"line":1,"column":1},"end":{"line":1,"column":1}},"children":[{"type":"text","value":"Figure 1. Average Study Time by Grade Group Across Four Datasets","position":{"start":{"line":1,"column":1},"end":{"line":1,"column":1}},"key":"yUpN5qohQu"}],"key":"IPChnKDwSt"}],"key":"tmVixLqDUj"}],"key":"Yp2ePkrucR"},{"type":"block","kind":"notebook-content","data":{"editable":true,"slideshow":{"slide_type":""},"tags":[]},"children":[{"type":"paragraph","position":{"start":{"line":1,"column":1},"end":{"line":2,"column":1}},"children":[{"type":"text","value":"Study time was chosen as the first indicator of strict lifestyle because it shows the students’ investment and prioritization of learning. Across four datasets, there is a consistent pattern: students in high grade groups spend more time studying, while low grade groups spend the least. However, the relationship is not similar across subjects. In the dataset 3, studying Mathematics report slightly more study time than those studying Portuguese. This is due to different learning demands of two subjects, as mathematics often requires more structured problem-solving tactics, while language relies heavily on continuous exposure, self-practicing and application in reality (","position":{"start":{"line":1,"column":1},"end":{"line":1,"column":1}},"key":"FgtpBzQqxF"},{"type":"cite","url":"https://doi.org/10.1002/curj.213","position":{"start":{"line":1,"column":1},"end":{"line":1,"column":1}},"children":[{"type":"text","value":"Foster (2023)","key":"poWIRvQwky"}],"kind":"narrative","label":"Foster_2023","identifier":"https://doi.org/10.1002/curj.213","enumerator":"1","key":"au1is0n5Ef"},{"type":"text","value":", ","position":{"start":{"line":1,"column":1},"end":{"line":1,"column":1}},"key":"DXyBrjxWI5"},{"type":"cite","url":"https://doi.org/10.1080/09588221.2020.1744666","position":{"start":{"line":1,"column":1},"end":{"line":1,"column":1}},"children":[{"type":"text","value":"Zhang & Zou (2020)","key":"i13uzJNErT"}],"kind":"narrative","label":"Zhang_2020","identifier":"https://doi.org/10.1080/09588221.2020.1744666","enumerator":"2","key":"RmB1iYZuys"},{"type":"text","value":").\nAlthough higher study time is correlated with higher academic performance, study time alone does not determine academic success. It can still depend on learning strategies, quality, attention, and motivation of students (","position":{"start":{"line":1,"column":1},"end":{"line":1,"column":1}},"key":"YkfbOqlsTj"},{"type":"cite","url":"https://doi.org/10.1007/s10212-012-0167-9","position":{"start":{"line":1,"column":1},"end":{"line":1,"column":1}},"children":[{"type":"text","value":"Rosário ","key":"BwpbQULwsT"},{"type":"emphasis","children":[{"type":"text","value":"et al.","key":"V0pX9QMXa9"}],"key":"YqC2FRplGA"},{"type":"text","value":" (2012)","key":"GiemVsLZkK"}],"kind":"narrative","label":"Ros_rio_2012","identifier":"https://doi.org/10.1007/s10212-012-0167-9","enumerator":"3","key":"lOP9AF9pVK"},{"type":"text","value":").","position":{"start":{"line":1,"column":1},"end":{"line":1,"column":1}},"key":"NBU8Agqjqz"}],"key":"tuY3WQDcTI"}],"visibility":"show","key":"f52UFbWab4"},{"type":"block","kind":"notebook-content","children":[{"type":"heading","depth":2,"position":{"start":{"line":1,"column":1},"end":{"line":1,"column":1}},"children":[{"type":"text","value":"Absence","position":{"start":{"line":1,"column":1},"end":{"line":1,"column":1}},"key":"MRMdVb8Rlb"}],"identifier":"absence","label":"Absence","html_id":"absence","implicit":true,"key":"wh8wZA8Eqx"},{"type":"paragraph","position":{"start":{"line":2,"column":1},"end":{"line":2,"column":1}},"children":[{"type":"text","value":"Students with fewer absences tend to achieve higher academic performance.","position":{"start":{"line":2,"column":1},"end":{"line":2,"column":1}},"key":"UjtEs4Cynh"}],"key":"ajjy64gfJo"}],"key":"CAsFTF465w"},{"type":"block","kind":"notebook-code","data":{"editable":true,"slideshow":{"slide_type":""},"tags":[]},"children":[{"type":"code","lang":"python","executable":true,"value":"%run ../plots/attendance_plot.ipynb","visibility":"remove","key":"yV9NJu6eLP"},{"type":"outputs","id":"BCfJebHoiuDiWMeWJknTG","children":[{"type":"output","jupyter_data":{"output_type":"display_data","metadata":{},"data":{"application/vnd.plotly.v1+json":{"content":"{\"config\":{\"plotlyServerURL\":\"https://plot.ly\"},\"data\":[{\"name\":\"Math\",\"type\":\"bar\",\"x\":[\"Low\",\"Medium\",\"High\"],\"y\":{\"bdata\":\"wQILLLDAGEBGKuZWZ6QaQD0K16NwPQ5A\",\"dtype\":\"f8\"}},{\"name\":\"Portuguese\",\"type\":\"bar\",\"x\":[\"Low\",\"Medium\",\"High\"],\"y\":{\"bdata\":\"chzHcRzHE0DGKbf7O7gMQBljjDHGGAdA\",\"dtype\":\"f8\"}}],\"layout\":{\"barmode\":\"group\",\"height\":550,\"legend\":{\"title\":{\"text\":\"Subject\"}},\"template\":{\"data\":{\"bar\":[{\"error_x\":{\"color\":\"#2a3f5f\"},\"error_y\":{\"color\":\"#2a3f5f\"},\"marker\":{\"line\":{\"color\":\"white\",\"width\":0.5},\"pattern\":{\"fillmode\":\"overlay\",\"size\":10,\"solidity\":0.2}},\"type\":\"bar\"}],\"barpolar\":[{\"marker\":{\"line\":{\"color\":\"white\",\"width\":0.5},\"pattern\":{\"fillmode\":\"overlay\",\"size\":10,\"solidity\":0.2}},\"type\":\"barpolar\"}],\"carpet\":[{\"aaxis\":{\"endlinecolor\":\"#2a3f5f\",\"gridcolor\":\"#C8D4E3\",\"linecolor\":\"#C8D4E3\",\"minorgridcolor\":\"#C8D4E3\",\"startlinecolor\":\"#2a3f5f\"},\"baxis\":{\"endlinecolor\":\"#2a3f5f\",\"gridcolor\":\"#C8D4E3\",\"linecolor\":\"#C8D4E3\",\"minorgridcolor\":\"#C8D4E3\",\"startlinecolor\":\"#2a3f5f\"},\"type\":\"carpet\"}],\"choropleth\":[{\"colorbar\":{\"outlinewidth\":0,\"ticks\":\"\"},\"type\":\"choropleth\"}],\"contour\":[{\"colorbar\":{\"outlinewidth\":0,\"ticks\":\"\"},\"colorscale\":[[0,\"#0d0887\"],[0.1111111111111111,\"#46039f\"],[0.2222222222222222,\"#7201a8\"],[0.3333333333333333,\"#9c179e\"],[0.4444444444444444,\"#bd3786\"],[0.5555555555555556,\"#d8576b\"],[0.6666666666666666,\"#ed7953\"],[0.7777777777777778,\"#fb9f3a\"],[0.8888888888888888,\"#fdca26\"],[1,\"#f0f921\"]],\"type\":\"contour\"}],\"contourcarpet\":[{\"colorbar\":{\"outlinewidth\":0,\"ticks\":\"\"},\"type\":\"contourcarpet\"}],\"heatmap\":[{\"colorbar\":{\"outlinewidth\":0,\"ticks\":\"\"},\"colorscale\":[[0,\"#0d0887\"],[0.1111111111111111,\"#46039f\"],[0.2222222222222222,\"#7201a8\"],[0.3333333333333333,\"#9c179e\"],[0.4444444444444444,\"#bd3786\"],[0.5555555555555556,\"#d8576b\"],[0.6666666666666666,\"#ed7953\"],[0.7777777777777778,\"#fb9f3a\"],[0.8888888888888888,\"#fdca26\"],[1,\"#f0f921\"]],\"type\":\"heatmap\"}],\"histogram\":[{\"marker\":{\"pattern\":{\"fillmode\":\"overlay\",\"size\":10,\"solidity\":0.2}},\"type\":\"histogram\"}],\"histogram2d\":[{\"colorbar\":{\"outlinewidth\":0,\"ticks\":\"\"},\"colorscale\":[[0,\"#0d0887\"],[0.1111111111111111,\"#46039f\"],[0.2222222222222222,\"#7201a8\"],[0.3333333333333333,\"#9c179e\"],[0.4444444444444444,\"#bd3786\"],[0.5555555555555556,\"#d8576b\"],[0.6666666666666666,\"#ed7953\"],[0.7777777777777778,\"#fb9f3a\"],[0.8888888888888888,\"#fdca26\"],[1,\"#f0f921\"]],\"type\":\"histogram2d\"}],\"histogram2dcontour\":[{\"colorbar\":{\"outlinewidth\":0,\"ticks\":\"\"},\"colorscale\":[[0,\"#0d0887\"],[0.1111111111111111,\"#46039f\"],[0.2222222222222222,\"#7201a8\"],[0.3333333333333333,\"#9c179e\"],[0.4444444444444444,\"#bd3786\"],[0.5555555555555556,\"#d8576b\"],[0.6666666666666666,\"#ed7953\"],[0.7777777777777778,\"#fb9f3a\"],[0.8888888888888888,\"#fdca26\"],[1,\"#f0f921\"]],\"type\":\"histogram2dcontour\"}],\"mesh3d\":[{\"colorbar\":{\"outlinewidth\":0,\"ticks\":\"\"},\"type\":\"mesh3d\"}],\"parcoords\":[{\"line\":{\"colorbar\":{\"outlinewidth\":0,\"ticks\":\"\"}},\"type\":\"parcoords\"}],\"pie\":[{\"automargin\":true,\"type\":\"pie\"}],\"scatter\":[{\"fillpattern\":{\"fillmode\":\"overlay\",\"size\":10,\"solidity\":0.2},\"type\":\"scatter\"}],\"scatter3d\":[{\"line\":{\"colorbar\":{\"outlinewidth\":0,\"ticks\":\"\"}},\"marker\":{\"colorbar\":{\"outlinewidth\":0,\"ticks\":\"\"}},\"type\":\"scatter3d\"}],\"scattercarpet\":[{\"marker\":{\"colorbar\":{\"outlinewidth\":0,\"ticks\":\"\"}},\"type\":\"scattercarpet\"}],\"scattergeo\":[{\"marker\":{\"colorbar\":{\"outlinewidth\":0,\"ticks\":\"\"}},\"type\":\"scattergeo\"}],\"scattergl\":[{\"marker\":{\"colorbar\":{\"outlinewidth\":0,\"ticks\":\"\"}},\"type\":\"scattergl\"}],\"scattermap\":[{\"marker\":{\"colorbar\":{\"outlinewidth\":0,\"ticks\":\"\"}},\"type\":\"scattermap\"}],\"scattermapbox\":[{\"marker\":{\"colorbar\":{\"outlinewidth\":0,\"ticks\":\"\"}},\"type\":\"scattermapbox\"}],\"scatterpolar\":[{\"marker\":{\"colorbar\":{\"outlinewidth\":0,\"ticks\":\"\"}},\"type\":\"scatterpolar\"}],\"scatterpolargl\":[{\"marker\":{\"colorbar\":{\"outlinewidth\":0,\"ticks\":\"\"}},\"type\":\"scatterpolargl\"}],\"scatterternary\":[{\"marker\":{\"colorbar\":{\"outlinewidth\":0,\"ticks\":\"\"}},\"type\":\"scatterternary\"}],\"surface\":[{\"colorbar\":{\"outlinewidth\":0,\"ticks\":\"\"},\"colorscale\":[[0,\"#0d0887\"],[0.1111111111111111,\"#46039f\"],[0.2222222222222222,\"#7201a8\"],[0.3333333333333333,\"#9c179e\"],[0.4444444444444444,\"#bd3786\"],[0.5555555555555556,\"#d8576b\"],[0.6666666666666666,\"#ed7953\"],[0.7777777777777778,\"#fb9f3a\"],[0.8888888888888888,\"#fdca26\"],[1,\"#f0f921\"]],\"type\":\"surface\"}],\"table\":[{\"cells\":{\"fill\":{\"color\":\"#EBF0F8\"},\"line\":{\"color\":\"white\"}},\"header\":{\"fill\":{\"color\":\"#C8D4E3\"},\"line\":{\"color\":\"white\"}},\"type\":\"table\"}]},\"layout\":{\"annotationdefaults\":{\"arrowcolor\":\"#2a3f5f\",\"arrowhead\":0,\"arrowwidth\":1},\"autotypenumbers\":\"strict\",\"coloraxis\":{\"colorbar\":{\"outlinewidth\":0,\"ticks\":\"\"}},\"colorscale\":{\"diverging\":[[0,\"#8e0152\"],[0.1,\"#c51b7d\"],[0.2,\"#de77ae\"],[0.3,\"#f1b6da\"],[0.4,\"#fde0ef\"],[0.5,\"#f7f7f7\"],[0.6,\"#e6f5d0\"],[0.7,\"#b8e186\"],[0.8,\"#7fbc41\"],[0.9,\"#4d9221\"],[1,\"#276419\"]],\"sequential\":[[0,\"#0d0887\"],[0.1111111111111111,\"#46039f\"],[0.2222222222222222,\"#7201a8\"],[0.3333333333333333,\"#9c179e\"],[0.4444444444444444,\"#bd3786\"],[0.5555555555555556,\"#d8576b\"],[0.6666666666666666,\"#ed7953\"],[0.7777777777777778,\"#fb9f3a\"],[0.8888888888888888,\"#fdca26\"],[1,\"#f0f921\"]],\"sequentialminus\":[[0,\"#0d0887\"],[0.1111111111111111,\"#46039f\"],[0.2222222222222222,\"#7201a8\"],[0.3333333333333333,\"#9c179e\"],[0.4444444444444444,\"#bd3786\"],[0.5555555555555556,\"#d8576b\"],[0.6666666666666666,\"#ed7953\"],[0.7777777777777778,\"#fb9f3a\"],[0.8888888888888888,\"#fdca26\"],[1,\"#f0f921\"]]},\"colorway\":[\"#636efa\",\"#EF553B\",\"#00cc96\",\"#ab63fa\",\"#FFA15A\",\"#19d3f3\",\"#FF6692\",\"#B6E880\",\"#FF97FF\",\"#FECB52\"],\"font\":{\"color\":\"#2a3f5f\"},\"geo\":{\"bgcolor\":\"white\",\"lakecolor\":\"white\",\"landcolor\":\"white\",\"showlakes\":true,\"showland\":true,\"subunitcolor\":\"#C8D4E3\"},\"hoverlabel\":{\"align\":\"left\"},\"hovermode\":\"closest\",\"mapbox\":{\"style\":\"light\"},\"paper_bgcolor\":\"white\",\"plot_bgcolor\":\"white\",\"polar\":{\"angularaxis\":{\"gridcolor\":\"#EBF0F8\",\"linecolor\":\"#EBF0F8\",\"ticks\":\"\"},\"bgcolor\":\"white\",\"radialaxis\":{\"gridcolor\":\"#EBF0F8\",\"linecolor\":\"#EBF0F8\",\"ticks\":\"\"}},\"scene\":{\"xaxis\":{\"backgroundcolor\":\"white\",\"gridcolor\":\"#DFE8F3\",\"gridwidth\":2,\"linecolor\":\"#EBF0F8\",\"showbackground\":true,\"ticks\":\"\",\"zerolinecolor\":\"#EBF0F8\"},\"yaxis\":{\"backgroundcolor\":\"white\",\"gridcolor\":\"#DFE8F3\",\"gridwidth\":2,\"linecolor\":\"#EBF0F8\",\"showbackground\":true,\"ticks\":\"\",\"zerolinecolor\":\"#EBF0F8\"},\"zaxis\":{\"backgroundcolor\":\"white\",\"gridcolor\":\"#DFE8F3\",\"gridwidth\":2,\"linecolor\":\"#EBF0F8\",\"showbackground\":true,\"ticks\":\"\",\"zerolinecolor\":\"#EBF0F8\"}},\"shapedefaults\":{\"line\":{\"color\":\"#2a3f5f\"}},\"ternary\":{\"aaxis\":{\"gridcolor\":\"#DFE8F3\",\"linecolor\":\"#A2B1C6\",\"ticks\":\"\"},\"baxis\":{\"gridcolor\":\"#DFE8F3\",\"linecolor\":\"#A2B1C6\",\"ticks\":\"\"},\"bgcolor\":\"white\",\"caxis\":{\"gridcolor\":\"#DFE8F3\",\"linecolor\":\"#A2B1C6\",\"ticks\":\"\"}},\"title\":{\"x\":0.05},\"xaxis\":{\"automargin\":true,\"gridcolor\":\"#EBF0F8\",\"linecolor\":\"#EBF0F8\",\"ticks\":\"\",\"title\":{\"standoff\":15},\"zerolinecolor\":\"#EBF0F8\",\"zerolinewidth\":2},\"yaxis\":{\"automargin\":true,\"gridcolor\":\"#EBF0F8\",\"linecolor\":\"#EBF0F8\",\"ticks\":\"\",\"title\":{\"standoff\":15},\"zerolinecolor\":\"#EBF0F8\",\"zerolinewidth\":2}}},\"width\":800,\"xaxis\":{\"title\":{\"text\":\"Grade Group\"}},\"yaxis\":{\"title\":{\"text\":\"Average Number of Absences\"}}}}","content_type":"application/vnd.plotly.v1+json"},"image/png":{"content_type":"image/png","hash":"6d70be66c6ad425f7b47f2db6060efff","path":"/6d70be66c6ad425f7b47f2db6060efff.png"},"text/html":{"content":"<div>            <script src=\"https://cdnjs.cloudflare.com/ajax/libs/mathjax/2.7.5/MathJax.js?config=TeX-AMS-MML_SVG\"></script><script>if (window.MathJax && window.MathJax.Hub && window.MathJax.Hub.Config) {window.MathJax.Hub.Config({SVG: {font: \"STIX-Web\"}});}</script>                <script>window.PlotlyConfig = {MathJaxConfig: 'local'};</script>\n        <script charset=\"utf-8\" src=\"https://cdn.plot.ly/plotly-3.5.0.min.js\" integrity=\"sha256-fHbNLP+GlIXN+efbQec78UkemUz3NJp7UmfGxC1tNxs=\" crossorigin=\"anonymous\"></script>                <div id=\"2a7267d6-22f3-4ef4-b2f7-2a7d5912666d\" class=\"plotly-graph-div\" style=\"height:550px; width:800px;\"></div>            <script>                window.PLOTLYENV=window.PLOTLYENV || {};                                if (document.getElementById(\"2a7267d6-22f3-4ef4-b2f7-2a7d5912666d\")) {                    Plotly.newPlot(                        \"2a7267d6-22f3-4ef4-b2f7-2a7d5912666d\",                        [{\"name\":\"Math\",\"x\":[\"Low\",\"Medium\",\"High\"],\"y\":{\"dtype\":\"f8\",\"bdata\":\"wQILLLDAGEBGKuZWZ6QaQD0K16NwPQ5A\"},\"type\":\"bar\"},{\"name\":\"Portuguese\",\"x\":[\"Low\",\"Medium\",\"High\"],\"y\":{\"dtype\":\"f8\",\"bdata\":\"chzHcRzHE0DGKbf7O7gMQBljjDHGGAdA\"},\"type\":\"bar\"}],                        {\"template\":{\"data\":{\"barpolar\":[{\"marker\":{\"line\":{\"color\":\"white\",\"width\":0.5},\"pattern\":{\"fillmode\":\"overlay\",\"size\":10,\"solidity\":0.2}},\"type\":\"barpolar\"}],\"bar\":[{\"error_x\":{\"color\":\"#2a3f5f\"},\"error_y\":{\"color\":\"#2a3f5f\"},\"marker\":{\"line\":{\"color\":\"white\",\"width\":0.5},\"pattern\":{\"fillmode\":\"overlay\",\"size\":10,\"solidity\":0.2}},\"type\":\"bar\"}],\"carpet\":[{\"aaxis\":{\"endlinecolor\":\"#2a3f5f\",\"gridcolor\":\"#C8D4E3\",\"linecolor\":\"#C8D4E3\",\"minorgridcolor\":\"#C8D4E3\",\"startlinecolor\":\"#2a3f5f\"},\"baxis\":{\"endlinecolor\":\"#2a3f5f\",\"gridcolor\":\"#C8D4E3\",\"linecolor\":\"#C8D4E3\",\"minorgridcolor\":\"#C8D4E3\",\"startlinecolor\":\"#2a3f5f\"},\"type\":\"carpet\"}],\"choropleth\":[{\"colorbar\":{\"outlinewidth\":0,\"ticks\":\"\"},\"type\":\"choropleth\"}],\"contourcarpet\":[{\"colorbar\":{\"outlinewidth\":0,\"ticks\":\"\"},\"type\":\"contourcarpet\"}],\"contour\":[{\"colorbar\":{\"outlinewidth\":0,\"ticks\":\"\"},\"colorscale\":[[0.0,\"#0d0887\"],[0.1111111111111111,\"#46039f\"],[0.2222222222222222,\"#7201a8\"],[0.3333333333333333,\"#9c179e\"],[0.4444444444444444,\"#bd3786\"],[0.5555555555555556,\"#d8576b\"],[0.6666666666666666,\"#ed7953\"],[0.7777777777777778,\"#fb9f3a\"],[0.8888888888888888,\"#fdca26\"],[1.0,\"#f0f921\"]],\"type\":\"contour\"}],\"heatmap\":[{\"colorbar\":{\"outlinewidth\":0,\"ticks\":\"\"},\"colorscale\":[[0.0,\"#0d0887\"],[0.1111111111111111,\"#46039f\"],[0.2222222222222222,\"#7201a8\"],[0.3333333333333333,\"#9c179e\"],[0.4444444444444444,\"#bd3786\"],[0.5555555555555556,\"#d8576b\"],[0.6666666666666666,\"#ed7953\"],[0.7777777777777778,\"#fb9f3a\"],[0.8888888888888888,\"#fdca26\"],[1.0,\"#f0f921\"]],\"type\":\"heatmap\"}],\"histogram2dcontour\":[{\"colorbar\":{\"outlinewidth\":0,\"ticks\":\"\"},\"colorscale\":[[0.0,\"#0d0887\"],[0.1111111111111111,\"#46039f\"],[0.2222222222222222,\"#7201a8\"],[0.3333333333333333,\"#9c179e\"],[0.4444444444444444,\"#bd3786\"],[0.5555555555555556,\"#d8576b\"],[0.6666666666666666,\"#ed7953\"],[0.7777777777777778,\"#fb9f3a\"],[0.8888888888888888,\"#fdca26\"],[1.0,\"#f0f921\"]],\"type\":\"histogram2dcontour\"}],\"histogram2d\":[{\"colorbar\":{\"outlinewidth\":0,\"ticks\":\"\"},\"colorscale\":[[0.0,\"#0d0887\"],[0.1111111111111111,\"#46039f\"],[0.2222222222222222,\"#7201a8\"],[0.3333333333333333,\"#9c179e\"],[0.4444444444444444,\"#bd3786\"],[0.5555555555555556,\"#d8576b\"],[0.6666666666666666,\"#ed7953\"],[0.7777777777777778,\"#fb9f3a\"],[0.8888888888888888,\"#fdca26\"],[1.0,\"#f0f921\"]],\"type\":\"histogram2d\"}],\"histogram\":[{\"marker\":{\"pattern\":{\"fillmode\":\"overlay\",\"size\":10,\"solidity\":0.2}},\"type\":\"histogram\"}],\"mesh3d\":[{\"colorbar\":{\"outlinewidth\":0,\"ticks\":\"\"},\"type\":\"mesh3d\"}],\"parcoords\":[{\"line\":{\"colorbar\":{\"outlinewidth\":0,\"ticks\":\"\"}},\"type\":\"parcoords\"}],\"pie\":[{\"automargin\":true,\"type\":\"pie\"}],\"scatter3d\":[{\"line\":{\"colorbar\":{\"outlinewidth\":0,\"ticks\":\"\"}},\"marker\":{\"colorbar\":{\"outlinewidth\":0,\"ticks\":\"\"}},\"type\":\"scatter3d\"}],\"scattercarpet\":[{\"marker\":{\"colorbar\":{\"outlinewidth\":0,\"ticks\":\"\"}},\"type\":\"scattercarpet\"}],\"scattergeo\":[{\"marker\":{\"colorbar\":{\"outlinewidth\":0,\"ticks\":\"\"}},\"type\":\"scattergeo\"}],\"scattergl\":[{\"marker\":{\"colorbar\":{\"outlinewidth\":0,\"ticks\":\"\"}},\"type\":\"scattergl\"}],\"scattermapbox\":[{\"marker\":{\"colorbar\":{\"outlinewidth\":0,\"ticks\":\"\"}},\"type\":\"scattermapbox\"}],\"scattermap\":[{\"marker\":{\"colorbar\":{\"outlinewidth\":0,\"ticks\":\"\"}},\"type\":\"scattermap\"}],\"scatterpolargl\":[{\"marker\":{\"colorbar\":{\"outlinewidth\":0,\"ticks\":\"\"}},\"type\":\"scatterpolargl\"}],\"scatterpolar\":[{\"marker\":{\"colorbar\":{\"outlinewidth\":0,\"ticks\":\"\"}},\"type\":\"scatterpolar\"}],\"scatter\":[{\"fillpattern\":{\"fillmode\":\"overlay\",\"size\":10,\"solidity\":0.2},\"type\":\"scatter\"}],\"scatterternary\":[{\"marker\":{\"colorbar\":{\"outlinewidth\":0,\"ticks\":\"\"}},\"type\":\"scatterternary\"}],\"surface\":[{\"colorbar\":{\"outlinewidth\":0,\"ticks\":\"\"},\"colorscale\":[[0.0,\"#0d0887\"],[0.1111111111111111,\"#46039f\"],[0.2222222222222222,\"#7201a8\"],[0.3333333333333333,\"#9c179e\"],[0.4444444444444444,\"#bd3786\"],[0.5555555555555556,\"#d8576b\"],[0.6666666666666666,\"#ed7953\"],[0.7777777777777778,\"#fb9f3a\"],[0.8888888888888888,\"#fdca26\"],[1.0,\"#f0f921\"]],\"type\":\"surface\"}],\"table\":[{\"cells\":{\"fill\":{\"color\":\"#EBF0F8\"},\"line\":{\"color\":\"white\"}},\"header\":{\"fill\":{\"color\":\"#C8D4E3\"},\"line\":{\"color\":\"white\"}},\"type\":\"table\"}]},\"layout\":{\"annotationdefaults\":{\"arrowcolor\":\"#2a3f5f\",\"arrowhead\":0,\"arrowwidth\":1},\"autotypenumbers\":\"strict\",\"coloraxis\":{\"colorbar\":{\"outlinewidth\":0,\"ticks\":\"\"}},\"colorscale\":{\"diverging\":[[0,\"#8e0152\"],[0.1,\"#c51b7d\"],[0.2,\"#de77ae\"],[0.3,\"#f1b6da\"],[0.4,\"#fde0ef\"],[0.5,\"#f7f7f7\"],[0.6,\"#e6f5d0\"],[0.7,\"#b8e186\"],[0.8,\"#7fbc41\"],[0.9,\"#4d9221\"],[1,\"#276419\"]],\"sequential\":[[0.0,\"#0d0887\"],[0.1111111111111111,\"#46039f\"],[0.2222222222222222,\"#7201a8\"],[0.3333333333333333,\"#9c179e\"],[0.4444444444444444,\"#bd3786\"],[0.5555555555555556,\"#d8576b\"],[0.6666666666666666,\"#ed7953\"],[0.7777777777777778,\"#fb9f3a\"],[0.8888888888888888,\"#fdca26\"],[1.0,\"#f0f921\"]],\"sequentialminus\":[[0.0,\"#0d0887\"],[0.1111111111111111,\"#46039f\"],[0.2222222222222222,\"#7201a8\"],[0.3333333333333333,\"#9c179e\"],[0.4444444444444444,\"#bd3786\"],[0.5555555555555556,\"#d8576b\"],[0.6666666666666666,\"#ed7953\"],[0.7777777777777778,\"#fb9f3a\"],[0.8888888888888888,\"#fdca26\"],[1.0,\"#f0f921\"]]},\"colorway\":[\"#636efa\",\"#EF553B\",\"#00cc96\",\"#ab63fa\",\"#FFA15A\",\"#19d3f3\",\"#FF6692\",\"#B6E880\",\"#FF97FF\",\"#FECB52\"],\"font\":{\"color\":\"#2a3f5f\"},\"geo\":{\"bgcolor\":\"white\",\"lakecolor\":\"white\",\"landcolor\":\"white\",\"showlakes\":true,\"showland\":true,\"subunitcolor\":\"#C8D4E3\"},\"hoverlabel\":{\"align\":\"left\"},\"hovermode\":\"closest\",\"mapbox\":{\"style\":\"light\"},\"paper_bgcolor\":\"white\",\"plot_bgcolor\":\"white\",\"polar\":{\"angularaxis\":{\"gridcolor\":\"#EBF0F8\",\"linecolor\":\"#EBF0F8\",\"ticks\":\"\"},\"bgcolor\":\"white\",\"radialaxis\":{\"gridcolor\":\"#EBF0F8\",\"linecolor\":\"#EBF0F8\",\"ticks\":\"\"}},\"scene\":{\"xaxis\":{\"backgroundcolor\":\"white\",\"gridcolor\":\"#DFE8F3\",\"gridwidth\":2,\"linecolor\":\"#EBF0F8\",\"showbackground\":true,\"ticks\":\"\",\"zerolinecolor\":\"#EBF0F8\"},\"yaxis\":{\"backgroundcolor\":\"white\",\"gridcolor\":\"#DFE8F3\",\"gridwidth\":2,\"linecolor\":\"#EBF0F8\",\"showbackground\":true,\"ticks\":\"\",\"zerolinecolor\":\"#EBF0F8\"},\"zaxis\":{\"backgroundcolor\":\"white\",\"gridcolor\":\"#DFE8F3\",\"gridwidth\":2,\"linecolor\":\"#EBF0F8\",\"showbackground\":true,\"ticks\":\"\",\"zerolinecolor\":\"#EBF0F8\"}},\"shapedefaults\":{\"line\":{\"color\":\"#2a3f5f\"}},\"ternary\":{\"aaxis\":{\"gridcolor\":\"#DFE8F3\",\"linecolor\":\"#A2B1C6\",\"ticks\":\"\"},\"baxis\":{\"gridcolor\":\"#DFE8F3\",\"linecolor\":\"#A2B1C6\",\"ticks\":\"\"},\"bgcolor\":\"white\",\"caxis\":{\"gridcolor\":\"#DFE8F3\",\"linecolor\":\"#A2B1C6\",\"ticks\":\"\"}},\"title\":{\"x\":0.05},\"xaxis\":{\"automargin\":true,\"gridcolor\":\"#EBF0F8\",\"linecolor\":\"#EBF0F8\",\"ticks\":\"\",\"title\":{\"standoff\":15},\"zerolinecolor\":\"#EBF0F8\",\"zerolinewidth\":2},\"yaxis\":{\"automargin\":true,\"gridcolor\":\"#EBF0F8\",\"linecolor\":\"#EBF0F8\",\"ticks\":\"\",\"title\":{\"standoff\":15},\"zerolinecolor\":\"#EBF0F8\",\"zerolinewidth\":2}}},\"legend\":{\"title\":{\"text\":\"Subject\"}},\"barmode\":\"group\",\"height\":550,\"width\":800,\"xaxis\":{\"title\":{\"text\":\"Grade Group\"}},\"yaxis\":{\"title\":{\"text\":\"Average Number of Absences\"}}},                        {\"responsive\": true}                    ).then(function(){\n                            \nvar gd = document.getElementById('2a7267d6-22f3-4ef4-b2f7-2a7d5912666d');\nvar x = new MutationObserver(function (mutations, observer) {{\n        var display = window.getComputedStyle(gd).display;\n        if (!display || display === 'none') {{\n            console.log([gd, 'removed!']);\n            Plotly.purge(gd);\n            observer.disconnect();\n        }}\n}});\n\n// Listen for the removal of the full notebook cells\nvar notebookContainer = gd.closest('#notebook-container');\nif (notebookContainer) {{\n    x.observe(notebookContainer, {childList: true});\n}}\n\n// Listen for the clearing of the current output cell\nvar outputEl = gd.closest('.output');\nif (outputEl) {{\n    x.observe(outputEl, {childList: true});\n}}\n\n                        })                };            </script>        </div>","content_type":"text/html"}}},"children":[],"key":"Yfrlww709W"}],"visibility":"show","key":"XGTdEfWJE6"}],"class":"col-page-right","visibility":"show","key":"HPaqNPugem"},{"type":"block","kind":"notebook-content","children":[{"type":"paragraph","position":{"start":{"line":1,"column":1},"end":{"line":1,"column":1}},"children":[{"type":"emphasis","position":{"start":{"line":1,"column":1},"end":{"line":1,"column":1}},"children":[{"type":"text","value":"Figure 2. Average Absences by Grade Group in Mathematics and Portuguese","position":{"start":{"line":1,"column":1},"end":{"line":1,"column":1}},"key":"KVekzopLnE"}],"key":"ZEmVFdRbiU"}],"key":"Ll5QBEekXj"}],"key":"jhQErAdB0H"},{"type":"block","kind":"notebook-content","children":[{"type":"paragraph","position":{"start":{"line":1,"column":1},"end":{"line":1,"column":1}},"children":[{"type":"text","value":"Figure 2 shows a clear relationship between study discipline and academic performance when measuring how many days students’ absences in the class. In both Mathematics and Portuguese, students in high grade group show fewest average absences, while medium and low grade groups are absent more frequently. ","position":{"start":{"line":1,"column":1},"end":{"line":1,"column":1}},"key":"gZ5bz9tQwD"},{"type":"cite","url":"https://doi.org/10.3102/0034654310362998","position":{"start":{"line":1,"column":1},"end":{"line":1,"column":1}},"children":[{"type":"text","value":"Credé ","key":"KngCO42ykQ"},{"type":"emphasis","children":[{"type":"text","value":"et al.","key":"Pf09SAZh9I"}],"key":"YN09CzZPcR"},{"type":"text","value":" (2010)","key":"N7eEUNQMpN"}],"kind":"narrative","label":"Cred__2010","identifier":"https://doi.org/10.3102/0034654310362998","enumerator":"4","key":"TjF5lMzoy6"},{"type":"text","value":" investigate that absenteeism can lead to lower grades, as missing classes reduces learning opportunities and classroom engagement. Moreover, mathematics students report more absences than Portuguese students across all grade groups, indicating slight differences in academic discipline between two subjects.","position":{"start":{"line":1,"column":1},"end":{"line":1,"column":1}},"key":"EEwUT2Wo34"}],"key":"uKBh8HL7EP"}],"key":"B76nuD8KLr"},{"type":"block","kind":"notebook-content","children":[{"type":"heading","depth":2,"position":{"start":{"line":1,"column":1},"end":{"line":1,"column":1}},"children":[{"type":"text","value":"Extra classes","position":{"start":{"line":1,"column":1},"end":{"line":1,"column":1}},"key":"uKqY9n989X"}],"identifier":"extra-classes","label":"Extra classes","html_id":"extra-classes","implicit":true,"key":"ARMrS4tCt5"},{"type":"paragraph","position":{"start":{"line":3,"column":1},"end":{"line":3,"column":1}},"children":[{"type":"emphasis","position":{"start":{"line":3,"column":1},"end":{"line":3,"column":1}},"children":[{"type":"text","value":"Students who get higher grades tend to combine intensive study time with extra classes","position":{"start":{"line":3,"column":1},"end":{"line":3,"column":1}},"key":"InyzuFHPIs"}],"key":"Fnd67dKkXf"}],"key":"OM1KNAeWVV"}],"key":"L0dmHoXlfh"},{"type":"block","kind":"notebook-code","data":{"editable":true,"slideshow":{"slide_type":""},"tags":[]},"children":[{"type":"code","lang":"python","executable":true,"value":"%run ../plots/extra_class_plot.ipynb","visibility":"remove","key":"JvIF3cxqeK"},{"type":"outputs","id":"rIFwtusRlaVs95NN-ia9L","children":[{"type":"output","jupyter_data":{"output_type":"display_data","metadata":{},"data":{"application/vnd.plotly.v1+json":{"content":"{\"config\":{\"plotlyServerURL\":\"https://plot.ly\"},\"data\":[{\"legendgroup\":\"no\",\"line\":{\"color\":\"#00CC96\"},\"marker\":{\"color\":\"#00CC96\"},\"mode\":\"lines+markers\",\"name\":\"no\",\"showlegend\":true,\"type\":\"scatter\",\"x\":{\"bdata\":\"AQIDBA==\",\"dtype\":\"i1\"},\"xaxis\":\"x\",\"y\":{\"bdata\":\"W7Zs2bJlI0BnSMzbGRIjQK211lprrSdAdNFFF110JUA=\",\"dtype\":\"f8\"},\"yaxis\":\"y\"},{\"legendgroup\":\"yes\",\"line\":{\"color\":\"#EF553B\"},\"marker\":{\"color\":\"#EF553B\"},\"mode\":\"lines+markers\",\"name\":\"yes\",\"showlegend\":true,\"type\":\"scatter\",\"x\":{\"bdata\":\"AQIDBA==\",\"dtype\":\"i1\"},\"xaxis\":\"x\",\"y\":{\"bdata\":\"AAAAAACwJUDzdobEvJ0lQAAAAAAAACZAAAAAAABAJ0A=\",\"dtype\":\"f8\"},\"yaxis\":\"y\"},{\"legendgroup\":\"no\",\"line\":{\"color\":\"#00CC96\"},\"marker\":{\"color\":\"#00CC96\"},\"mode\":\"lines+markers\",\"name\":\"no\",\"showlegend\":false,\"type\":\"scatter\",\"x\":{\"bdata\":\"AQIDBA==\",\"dtype\":\"i1\"},\"xaxis\":\"x2\",\"y\":{\"bdata\":\"zZcmDmO1JUCfaWv83TwoQLbWWmuttSpAAAAAAABgKkA=\",\"dtype\":\"f8\"},\"yaxis\":\"y2\"},{\"legendgroup\":\"yes\",\"line\":{\"color\":\"#EF553B\"},\"marker\":{\"color\":\"#EF553B\"},\"mode\":\"lines+markers\",\"name\":\"yes\",\"showlegend\":false,\"type\":\"scatter\",\"x\":{\"bdata\":\"AQIDBA==\",\"dtype\":\"i1\"},\"xaxis\":\"x2\",\"y\":{\"bdata\":\"J3ZiJ3ZiJUDlNZTXUF4nQAAAAAAAgCRAVVVVVVVVJ0A=\",\"dtype\":\"f8\"},\"yaxis\":\"y2\"}],\"layout\":{\"annotations\":[{\"font\":{\"size\":16},\"showarrow\":false,\"text\":\"Math\",\"x\":0.22,\"xanchor\":\"center\",\"xref\":\"paper\",\"y\":1,\"yanchor\":\"bottom\",\"yref\":\"paper\"},{\"font\":{\"size\":16},\"showarrow\":false,\"text\":\"Portuguese\",\"x\":0.78,\"xanchor\":\"center\",\"xref\":\"paper\",\"y\":1,\"yanchor\":\"bottom\",\"yref\":\"paper\"}],\"height\":450,\"legend\":{\"title\":{\"text\":\"Paid Extra Classes\"}},\"template\":{\"data\":{\"bar\":[{\"error_x\":{\"color\":\"#2a3f5f\"},\"error_y\":{\"color\":\"#2a3f5f\"},\"marker\":{\"line\":{\"color\":\"white\",\"width\":0.5},\"pattern\":{\"fillmode\":\"overlay\",\"size\":10,\"solidity\":0.2}},\"type\":\"bar\"}],\"barpolar\":[{\"marker\":{\"line\":{\"color\":\"white\",\"width\":0.5},\"pattern\":{\"fillmode\":\"overlay\",\"size\":10,\"solidity\":0.2}},\"type\":\"barpolar\"}],\"carpet\":[{\"aaxis\":{\"endlinecolor\":\"#2a3f5f\",\"gridcolor\":\"#C8D4E3\",\"linecolor\":\"#C8D4E3\",\"minorgridcolor\":\"#C8D4E3\",\"startlinecolor\":\"#2a3f5f\"},\"baxis\":{\"endlinecolor\":\"#2a3f5f\",\"gridcolor\":\"#C8D4E3\",\"linecolor\":\"#C8D4E3\",\"minorgridcolor\":\"#C8D4E3\",\"startlinecolor\":\"#2a3f5f\"},\"type\":\"carpet\"}],\"choropleth\":[{\"colorbar\":{\"outlinewidth\":0,\"ticks\":\"\"},\"type\":\"choropleth\"}],\"contour\":[{\"colorbar\":{\"outlinewidth\":0,\"ticks\":\"\"},\"colorscale\":[[0,\"#0d0887\"],[0.1111111111111111,\"#46039f\"],[0.2222222222222222,\"#7201a8\"],[0.3333333333333333,\"#9c179e\"],[0.4444444444444444,\"#bd3786\"],[0.5555555555555556,\"#d8576b\"],[0.6666666666666666,\"#ed7953\"],[0.7777777777777778,\"#fb9f3a\"],[0.8888888888888888,\"#fdca26\"],[1,\"#f0f921\"]],\"type\":\"contour\"}],\"contourcarpet\":[{\"colorbar\":{\"outlinewidth\":0,\"ticks\":\"\"},\"type\":\"contourcarpet\"}],\"heatmap\":[{\"colorbar\":{\"outlinewidth\":0,\"ticks\":\"\"},\"colorscale\":[[0,\"#0d0887\"],[0.1111111111111111,\"#46039f\"],[0.2222222222222222,\"#7201a8\"],[0.3333333333333333,\"#9c179e\"],[0.4444444444444444,\"#bd3786\"],[0.5555555555555556,\"#d8576b\"],[0.6666666666666666,\"#ed7953\"],[0.7777777777777778,\"#fb9f3a\"],[0.8888888888888888,\"#fdca26\"],[1,\"#f0f921\"]],\"type\":\"heatmap\"}],\"histogram\":[{\"marker\":{\"pattern\":{\"fillmode\":\"overlay\",\"size\":10,\"solidity\":0.2}},\"type\":\"histogram\"}],\"histogram2d\":[{\"colorbar\":{\"outlinewidth\":0,\"ticks\":\"\"},\"colorscale\":[[0,\"#0d0887\"],[0.1111111111111111,\"#46039f\"],[0.2222222222222222,\"#7201a8\"],[0.3333333333333333,\"#9c179e\"],[0.4444444444444444,\"#bd3786\"],[0.5555555555555556,\"#d8576b\"],[0.6666666666666666,\"#ed7953\"],[0.7777777777777778,\"#fb9f3a\"],[0.8888888888888888,\"#fdca26\"],[1,\"#f0f921\"]],\"type\":\"histogram2d\"}],\"histogram2dcontour\":[{\"colorbar\":{\"outlinewidth\":0,\"ticks\":\"\"},\"colorscale\":[[0,\"#0d0887\"],[0.1111111111111111,\"#46039f\"],[0.2222222222222222,\"#7201a8\"],[0.3333333333333333,\"#9c179e\"],[0.4444444444444444,\"#bd3786\"],[0.5555555555555556,\"#d8576b\"],[0.6666666666666666,\"#ed7953\"],[0.7777777777777778,\"#fb9f3a\"],[0.8888888888888888,\"#fdca26\"],[1,\"#f0f921\"]],\"type\":\"histogram2dcontour\"}],\"mesh3d\":[{\"colorbar\":{\"outlinewidth\":0,\"ticks\":\"\"},\"type\":\"mesh3d\"}],\"parcoords\":[{\"line\":{\"colorbar\":{\"outlinewidth\":0,\"ticks\":\"\"}},\"type\":\"parcoords\"}],\"pie\":[{\"automargin\":true,\"type\":\"pie\"}],\"scatter\":[{\"fillpattern\":{\"fillmode\":\"overlay\",\"size\":10,\"solidity\":0.2},\"type\":\"scatter\"}],\"scatter3d\":[{\"line\":{\"colorbar\":{\"outlinewidth\":0,\"ticks\":\"\"}},\"marker\":{\"colorbar\":{\"outlinewidth\":0,\"ticks\":\"\"}},\"type\":\"scatter3d\"}],\"scattercarpet\":[{\"marker\":{\"colorbar\":{\"outlinewidth\":0,\"ticks\":\"\"}},\"type\":\"scattercarpet\"}],\"scattergeo\":[{\"marker\":{\"colorbar\":{\"outlinewidth\":0,\"ticks\":\"\"}},\"type\":\"scattergeo\"}],\"scattergl\":[{\"marker\":{\"colorbar\":{\"outlinewidth\":0,\"ticks\":\"\"}},\"type\":\"scattergl\"}],\"scattermap\":[{\"marker\":{\"colorbar\":{\"outlinewidth\":0,\"ticks\":\"\"}},\"type\":\"scattermap\"}],\"scattermapbox\":[{\"marker\":{\"colorbar\":{\"outlinewidth\":0,\"ticks\":\"\"}},\"type\":\"scattermapbox\"}],\"scatterpolar\":[{\"marker\":{\"colorbar\":{\"outlinewidth\":0,\"ticks\":\"\"}},\"type\":\"scatterpolar\"}],\"scatterpolargl\":[{\"marker\":{\"colorbar\":{\"outlinewidth\":0,\"ticks\":\"\"}},\"type\":\"scatterpolargl\"}],\"scatterternary\":[{\"marker\":{\"colorbar\":{\"outlinewidth\":0,\"ticks\":\"\"}},\"type\":\"scatterternary\"}],\"surface\":[{\"colorbar\":{\"outlinewidth\":0,\"ticks\":\"\"},\"colorscale\":[[0,\"#0d0887\"],[0.1111111111111111,\"#46039f\"],[0.2222222222222222,\"#7201a8\"],[0.3333333333333333,\"#9c179e\"],[0.4444444444444444,\"#bd3786\"],[0.5555555555555556,\"#d8576b\"],[0.6666666666666666,\"#ed7953\"],[0.7777777777777778,\"#fb9f3a\"],[0.8888888888888888,\"#fdca26\"],[1,\"#f0f921\"]],\"type\":\"surface\"}],\"table\":[{\"cells\":{\"fill\":{\"color\":\"#EBF0F8\"},\"line\":{\"color\":\"white\"}},\"header\":{\"fill\":{\"color\":\"#C8D4E3\"},\"line\":{\"color\":\"white\"}},\"type\":\"table\"}]},\"layout\":{\"annotationdefaults\":{\"arrowcolor\":\"#2a3f5f\",\"arrowhead\":0,\"arrowwidth\":1},\"autotypenumbers\":\"strict\",\"coloraxis\":{\"colorbar\":{\"outlinewidth\":0,\"ticks\":\"\"}},\"colorscale\":{\"diverging\":[[0,\"#8e0152\"],[0.1,\"#c51b7d\"],[0.2,\"#de77ae\"],[0.3,\"#f1b6da\"],[0.4,\"#fde0ef\"],[0.5,\"#f7f7f7\"],[0.6,\"#e6f5d0\"],[0.7,\"#b8e186\"],[0.8,\"#7fbc41\"],[0.9,\"#4d9221\"],[1,\"#276419\"]],\"sequential\":[[0,\"#0d0887\"],[0.1111111111111111,\"#46039f\"],[0.2222222222222222,\"#7201a8\"],[0.3333333333333333,\"#9c179e\"],[0.4444444444444444,\"#bd3786\"],[0.5555555555555556,\"#d8576b\"],[0.6666666666666666,\"#ed7953\"],[0.7777777777777778,\"#fb9f3a\"],[0.8888888888888888,\"#fdca26\"],[1,\"#f0f921\"]],\"sequentialminus\":[[0,\"#0d0887\"],[0.1111111111111111,\"#46039f\"],[0.2222222222222222,\"#7201a8\"],[0.3333333333333333,\"#9c179e\"],[0.4444444444444444,\"#bd3786\"],[0.5555555555555556,\"#d8576b\"],[0.6666666666666666,\"#ed7953\"],[0.7777777777777778,\"#fb9f3a\"],[0.8888888888888888,\"#fdca26\"],[1,\"#f0f921\"]]},\"colorway\":[\"#636efa\",\"#EF553B\",\"#00cc96\",\"#ab63fa\",\"#FFA15A\",\"#19d3f3\",\"#FF6692\",\"#B6E880\",\"#FF97FF\",\"#FECB52\"],\"font\":{\"color\":\"#2a3f5f\"},\"geo\":{\"bgcolor\":\"white\",\"lakecolor\":\"white\",\"landcolor\":\"white\",\"showlakes\":true,\"showland\":true,\"subunitcolor\":\"#C8D4E3\"},\"hoverlabel\":{\"align\":\"left\"},\"hovermode\":\"closest\",\"mapbox\":{\"style\":\"light\"},\"paper_bgcolor\":\"white\",\"plot_bgcolor\":\"white\",\"polar\":{\"angularaxis\":{\"gridcolor\":\"#EBF0F8\",\"linecolor\":\"#EBF0F8\",\"ticks\":\"\"},\"bgcolor\":\"white\",\"radialaxis\":{\"gridcolor\":\"#EBF0F8\",\"linecolor\":\"#EBF0F8\",\"ticks\":\"\"}},\"scene\":{\"xaxis\":{\"backgroundcolor\":\"white\",\"gridcolor\":\"#DFE8F3\",\"gridwidth\":2,\"linecolor\":\"#EBF0F8\",\"showbackground\":true,\"ticks\":\"\",\"zerolinecolor\":\"#EBF0F8\"},\"yaxis\":{\"backgroundcolor\":\"white\",\"gridcolor\":\"#DFE8F3\",\"gridwidth\":2,\"linecolor\":\"#EBF0F8\",\"showbackground\":true,\"ticks\":\"\",\"zerolinecolor\":\"#EBF0F8\"},\"zaxis\":{\"backgroundcolor\":\"white\",\"gridcolor\":\"#DFE8F3\",\"gridwidth\":2,\"linecolor\":\"#EBF0F8\",\"showbackground\":true,\"ticks\":\"\",\"zerolinecolor\":\"#EBF0F8\"}},\"shapedefaults\":{\"line\":{\"color\":\"#2a3f5f\"}},\"ternary\":{\"aaxis\":{\"gridcolor\":\"#DFE8F3\",\"linecolor\":\"#A2B1C6\",\"ticks\":\"\"},\"baxis\":{\"gridcolor\":\"#DFE8F3\",\"linecolor\":\"#A2B1C6\",\"ticks\":\"\"},\"bgcolor\":\"white\",\"caxis\":{\"gridcolor\":\"#DFE8F3\",\"linecolor\":\"#A2B1C6\",\"ticks\":\"\"}},\"title\":{\"x\":0.05},\"xaxis\":{\"automargin\":true,\"gridcolor\":\"#EBF0F8\",\"linecolor\":\"#EBF0F8\",\"ticks\":\"\",\"title\":{\"standoff\":15},\"zerolinecolor\":\"#EBF0F8\",\"zerolinewidth\":2},\"yaxis\":{\"automargin\":true,\"gridcolor\":\"#EBF0F8\",\"linecolor\":\"#EBF0F8\",\"ticks\":\"\",\"title\":{\"standoff\":15},\"zerolinecolor\":\"#EBF0F8\",\"zerolinewidth\":2}}},\"width\":1000,\"xaxis\":{\"anchor\":\"y\",\"domain\":[0,0.44],\"tickmode\":\"array\",\"tickvals\":[1,2,3,4],\"title\":{\"text\":\"Study Time\"}},\"xaxis2\":{\"anchor\":\"y2\",\"domain\":[0.56,1],\"tickmode\":\"array\",\"tickvals\":[1,2,3,4],\"title\":{\"text\":\"Study Time\"}},\"yaxis\":{\"anchor\":\"x\",\"domain\":[0,1],\"title\":{\"text\":\"Average Final Grade (G3)\"}},\"yaxis2\":{\"anchor\":\"x2\",\"domain\":[0,1],\"title\":{\"text\":\"Average Final Grade (G3)\"}}}}","content_type":"application/vnd.plotly.v1+json"},"image/png":{"content_type":"image/png","hash":"dbe74b78a02bc6e028c359700076bef0","path":"/dbe74b78a02bc6e028c359700076bef0.png"},"text/html":{"content":"<div>            <script src=\"https://cdnjs.cloudflare.com/ajax/libs/mathjax/2.7.5/MathJax.js?config=TeX-AMS-MML_SVG\"></script><script>if (window.MathJax && window.MathJax.Hub && window.MathJax.Hub.Config) {window.MathJax.Hub.Config({SVG: {font: \"STIX-Web\"}});}</script>                <script>window.PlotlyConfig = {MathJaxConfig: 'local'};</script>\n        <script charset=\"utf-8\" src=\"https://cdn.plot.ly/plotly-3.5.0.min.js\" integrity=\"sha256-fHbNLP+GlIXN+efbQec78UkemUz3NJp7UmfGxC1tNxs=\" crossorigin=\"anonymous\"></script>                <div id=\"8a5a029a-c0ae-45df-800e-861dfc0d305b\" class=\"plotly-graph-div\" style=\"height:450px; width:1000px;\"></div>            <script>                window.PLOTLYENV=window.PLOTLYENV || {};                                if (document.getElementById(\"8a5a029a-c0ae-45df-800e-861dfc0d305b\")) {                    Plotly.newPlot(                        \"8a5a029a-c0ae-45df-800e-861dfc0d305b\",                        [{\"legendgroup\":\"no\",\"line\":{\"color\":\"#00CC96\"},\"marker\":{\"color\":\"#00CC96\"},\"mode\":\"lines+markers\",\"name\":\"no\",\"showlegend\":true,\"x\":{\"dtype\":\"i1\",\"bdata\":\"AQIDBA==\"},\"y\":{\"dtype\":\"f8\",\"bdata\":\"W7Zs2bJlI0BnSMzbGRIjQK211lprrSdAdNFFF110JUA=\"},\"type\":\"scatter\",\"xaxis\":\"x\",\"yaxis\":\"y\"},{\"legendgroup\":\"yes\",\"line\":{\"color\":\"#EF553B\"},\"marker\":{\"color\":\"#EF553B\"},\"mode\":\"lines+markers\",\"name\":\"yes\",\"showlegend\":true,\"x\":{\"dtype\":\"i1\",\"bdata\":\"AQIDBA==\"},\"y\":{\"dtype\":\"f8\",\"bdata\":\"AAAAAACwJUDzdobEvJ0lQAAAAAAAACZAAAAAAABAJ0A=\"},\"type\":\"scatter\",\"xaxis\":\"x\",\"yaxis\":\"y\"},{\"legendgroup\":\"no\",\"line\":{\"color\":\"#00CC96\"},\"marker\":{\"color\":\"#00CC96\"},\"mode\":\"lines+markers\",\"name\":\"no\",\"showlegend\":false,\"x\":{\"dtype\":\"i1\",\"bdata\":\"AQIDBA==\"},\"y\":{\"dtype\":\"f8\",\"bdata\":\"zZcmDmO1JUCfaWv83TwoQLbWWmuttSpAAAAAAABgKkA=\"},\"type\":\"scatter\",\"xaxis\":\"x2\",\"yaxis\":\"y2\"},{\"legendgroup\":\"yes\",\"line\":{\"color\":\"#EF553B\"},\"marker\":{\"color\":\"#EF553B\"},\"mode\":\"lines+markers\",\"name\":\"yes\",\"showlegend\":false,\"x\":{\"dtype\":\"i1\",\"bdata\":\"AQIDBA==\"},\"y\":{\"dtype\":\"f8\",\"bdata\":\"J3ZiJ3ZiJUDlNZTXUF4nQAAAAAAAgCRAVVVVVVVVJ0A=\"},\"type\":\"scatter\",\"xaxis\":\"x2\",\"yaxis\":\"y2\"}],                        {\"template\":{\"data\":{\"barpolar\":[{\"marker\":{\"line\":{\"color\":\"white\",\"width\":0.5},\"pattern\":{\"fillmode\":\"overlay\",\"size\":10,\"solidity\":0.2}},\"type\":\"barpolar\"}],\"bar\":[{\"error_x\":{\"color\":\"#2a3f5f\"},\"error_y\":{\"color\":\"#2a3f5f\"},\"marker\":{\"line\":{\"color\":\"white\",\"width\":0.5},\"pattern\":{\"fillmode\":\"overlay\",\"size\":10,\"solidity\":0.2}},\"type\":\"bar\"}],\"carpet\":[{\"aaxis\":{\"endlinecolor\":\"#2a3f5f\",\"gridcolor\":\"#C8D4E3\",\"linecolor\":\"#C8D4E3\",\"minorgridcolor\":\"#C8D4E3\",\"startlinecolor\":\"#2a3f5f\"},\"baxis\":{\"endlinecolor\":\"#2a3f5f\",\"gridcolor\":\"#C8D4E3\",\"linecolor\":\"#C8D4E3\",\"minorgridcolor\":\"#C8D4E3\",\"startlinecolor\":\"#2a3f5f\"},\"type\":\"carpet\"}],\"choropleth\":[{\"colorbar\":{\"outlinewidth\":0,\"ticks\":\"\"},\"type\":\"choropleth\"}],\"contourcarpet\":[{\"colorbar\":{\"outlinewidth\":0,\"ticks\":\"\"},\"type\":\"contourcarpet\"}],\"contour\":[{\"colorbar\":{\"outlinewidth\":0,\"ticks\":\"\"},\"colorscale\":[[0.0,\"#0d0887\"],[0.1111111111111111,\"#46039f\"],[0.2222222222222222,\"#7201a8\"],[0.3333333333333333,\"#9c179e\"],[0.4444444444444444,\"#bd3786\"],[0.5555555555555556,\"#d8576b\"],[0.6666666666666666,\"#ed7953\"],[0.7777777777777778,\"#fb9f3a\"],[0.8888888888888888,\"#fdca26\"],[1.0,\"#f0f921\"]],\"type\":\"contour\"}],\"heatmap\":[{\"colorbar\":{\"outlinewidth\":0,\"ticks\":\"\"},\"colorscale\":[[0.0,\"#0d0887\"],[0.1111111111111111,\"#46039f\"],[0.2222222222222222,\"#7201a8\"],[0.3333333333333333,\"#9c179e\"],[0.4444444444444444,\"#bd3786\"],[0.5555555555555556,\"#d8576b\"],[0.6666666666666666,\"#ed7953\"],[0.7777777777777778,\"#fb9f3a\"],[0.8888888888888888,\"#fdca26\"],[1.0,\"#f0f921\"]],\"type\":\"heatmap\"}],\"histogram2dcontour\":[{\"colorbar\":{\"outlinewidth\":0,\"ticks\":\"\"},\"colorscale\":[[0.0,\"#0d0887\"],[0.1111111111111111,\"#46039f\"],[0.2222222222222222,\"#7201a8\"],[0.3333333333333333,\"#9c179e\"],[0.4444444444444444,\"#bd3786\"],[0.5555555555555556,\"#d8576b\"],[0.6666666666666666,\"#ed7953\"],[0.7777777777777778,\"#fb9f3a\"],[0.8888888888888888,\"#fdca26\"],[1.0,\"#f0f921\"]],\"type\":\"histogram2dcontour\"}],\"histogram2d\":[{\"colorbar\":{\"outlinewidth\":0,\"ticks\":\"\"},\"colorscale\":[[0.0,\"#0d0887\"],[0.1111111111111111,\"#46039f\"],[0.2222222222222222,\"#7201a8\"],[0.3333333333333333,\"#9c179e\"],[0.4444444444444444,\"#bd3786\"],[0.5555555555555556,\"#d8576b\"],[0.6666666666666666,\"#ed7953\"],[0.7777777777777778,\"#fb9f3a\"],[0.8888888888888888,\"#fdca26\"],[1.0,\"#f0f921\"]],\"type\":\"histogram2d\"}],\"histogram\":[{\"marker\":{\"pattern\":{\"fillmode\":\"overlay\",\"size\":10,\"solidity\":0.2}},\"type\":\"histogram\"}],\"mesh3d\":[{\"colorbar\":{\"outlinewidth\":0,\"ticks\":\"\"},\"type\":\"mesh3d\"}],\"parcoords\":[{\"line\":{\"colorbar\":{\"outlinewidth\":0,\"ticks\":\"\"}},\"type\":\"parcoords\"}],\"pie\":[{\"automargin\":true,\"type\":\"pie\"}],\"scatter3d\":[{\"line\":{\"colorbar\":{\"outlinewidth\":0,\"ticks\":\"\"}},\"marker\":{\"colorbar\":{\"outlinewidth\":0,\"ticks\":\"\"}},\"type\":\"scatter3d\"}],\"scattercarpet\":[{\"marker\":{\"colorbar\":{\"outlinewidth\":0,\"ticks\":\"\"}},\"type\":\"scattercarpet\"}],\"scattergeo\":[{\"marker\":{\"colorbar\":{\"outlinewidth\":0,\"ticks\":\"\"}},\"type\":\"scattergeo\"}],\"scattergl\":[{\"marker\":{\"colorbar\":{\"outlinewidth\":0,\"ticks\":\"\"}},\"type\":\"scattergl\"}],\"scattermapbox\":[{\"marker\":{\"colorbar\":{\"outlinewidth\":0,\"ticks\":\"\"}},\"type\":\"scattermapbox\"}],\"scattermap\":[{\"marker\":{\"colorbar\":{\"outlinewidth\":0,\"ticks\":\"\"}},\"type\":\"scattermap\"}],\"scatterpolargl\":[{\"marker\":{\"colorbar\":{\"outlinewidth\":0,\"ticks\":\"\"}},\"type\":\"scatterpolargl\"}],\"scatterpolar\":[{\"marker\":{\"colorbar\":{\"outlinewidth\":0,\"ticks\":\"\"}},\"type\":\"scatterpolar\"}],\"scatter\":[{\"fillpattern\":{\"fillmode\":\"overlay\",\"size\":10,\"solidity\":0.2},\"type\":\"scatter\"}],\"scatterternary\":[{\"marker\":{\"colorbar\":{\"outlinewidth\":0,\"ticks\":\"\"}},\"type\":\"scatterternary\"}],\"surface\":[{\"colorbar\":{\"outlinewidth\":0,\"ticks\":\"\"},\"colorscale\":[[0.0,\"#0d0887\"],[0.1111111111111111,\"#46039f\"],[0.2222222222222222,\"#7201a8\"],[0.3333333333333333,\"#9c179e\"],[0.4444444444444444,\"#bd3786\"],[0.5555555555555556,\"#d8576b\"],[0.6666666666666666,\"#ed7953\"],[0.7777777777777778,\"#fb9f3a\"],[0.8888888888888888,\"#fdca26\"],[1.0,\"#f0f921\"]],\"type\":\"surface\"}],\"table\":[{\"cells\":{\"fill\":{\"color\":\"#EBF0F8\"},\"line\":{\"color\":\"white\"}},\"header\":{\"fill\":{\"color\":\"#C8D4E3\"},\"line\":{\"color\":\"white\"}},\"type\":\"table\"}]},\"layout\":{\"annotationdefaults\":{\"arrowcolor\":\"#2a3f5f\",\"arrowhead\":0,\"arrowwidth\":1},\"autotypenumbers\":\"strict\",\"coloraxis\":{\"colorbar\":{\"outlinewidth\":0,\"ticks\":\"\"}},\"colorscale\":{\"diverging\":[[0,\"#8e0152\"],[0.1,\"#c51b7d\"],[0.2,\"#de77ae\"],[0.3,\"#f1b6da\"],[0.4,\"#fde0ef\"],[0.5,\"#f7f7f7\"],[0.6,\"#e6f5d0\"],[0.7,\"#b8e186\"],[0.8,\"#7fbc41\"],[0.9,\"#4d9221\"],[1,\"#276419\"]],\"sequential\":[[0.0,\"#0d0887\"],[0.1111111111111111,\"#46039f\"],[0.2222222222222222,\"#7201a8\"],[0.3333333333333333,\"#9c179e\"],[0.4444444444444444,\"#bd3786\"],[0.5555555555555556,\"#d8576b\"],[0.6666666666666666,\"#ed7953\"],[0.7777777777777778,\"#fb9f3a\"],[0.8888888888888888,\"#fdca26\"],[1.0,\"#f0f921\"]],\"sequentialminus\":[[0.0,\"#0d0887\"],[0.1111111111111111,\"#46039f\"],[0.2222222222222222,\"#7201a8\"],[0.3333333333333333,\"#9c179e\"],[0.4444444444444444,\"#bd3786\"],[0.5555555555555556,\"#d8576b\"],[0.6666666666666666,\"#ed7953\"],[0.7777777777777778,\"#fb9f3a\"],[0.8888888888888888,\"#fdca26\"],[1.0,\"#f0f921\"]]},\"colorway\":[\"#636efa\",\"#EF553B\",\"#00cc96\",\"#ab63fa\",\"#FFA15A\",\"#19d3f3\",\"#FF6692\",\"#B6E880\",\"#FF97FF\",\"#FECB52\"],\"font\":{\"color\":\"#2a3f5f\"},\"geo\":{\"bgcolor\":\"white\",\"lakecolor\":\"white\",\"landcolor\":\"white\",\"showlakes\":true,\"showland\":true,\"subunitcolor\":\"#C8D4E3\"},\"hoverlabel\":{\"align\":\"left\"},\"hovermode\":\"closest\",\"mapbox\":{\"style\":\"light\"},\"paper_bgcolor\":\"white\",\"plot_bgcolor\":\"white\",\"polar\":{\"angularaxis\":{\"gridcolor\":\"#EBF0F8\",\"linecolor\":\"#EBF0F8\",\"ticks\":\"\"},\"bgcolor\":\"white\",\"radialaxis\":{\"gridcolor\":\"#EBF0F8\",\"linecolor\":\"#EBF0F8\",\"ticks\":\"\"}},\"scene\":{\"xaxis\":{\"backgroundcolor\":\"white\",\"gridcolor\":\"#DFE8F3\",\"gridwidth\":2,\"linecolor\":\"#EBF0F8\",\"showbackground\":true,\"ticks\":\"\",\"zerolinecolor\":\"#EBF0F8\"},\"yaxis\":{\"backgroundcolor\":\"white\",\"gridcolor\":\"#DFE8F3\",\"gridwidth\":2,\"linecolor\":\"#EBF0F8\",\"showbackground\":true,\"ticks\":\"\",\"zerolinecolor\":\"#EBF0F8\"},\"zaxis\":{\"backgroundcolor\":\"white\",\"gridcolor\":\"#DFE8F3\",\"gridwidth\":2,\"linecolor\":\"#EBF0F8\",\"showbackground\":true,\"ticks\":\"\",\"zerolinecolor\":\"#EBF0F8\"}},\"shapedefaults\":{\"line\":{\"color\":\"#2a3f5f\"}},\"ternary\":{\"aaxis\":{\"gridcolor\":\"#DFE8F3\",\"linecolor\":\"#A2B1C6\",\"ticks\":\"\"},\"baxis\":{\"gridcolor\":\"#DFE8F3\",\"linecolor\":\"#A2B1C6\",\"ticks\":\"\"},\"bgcolor\":\"white\",\"caxis\":{\"gridcolor\":\"#DFE8F3\",\"linecolor\":\"#A2B1C6\",\"ticks\":\"\"}},\"title\":{\"x\":0.05},\"xaxis\":{\"automargin\":true,\"gridcolor\":\"#EBF0F8\",\"linecolor\":\"#EBF0F8\",\"ticks\":\"\",\"title\":{\"standoff\":15},\"zerolinecolor\":\"#EBF0F8\",\"zerolinewidth\":2},\"yaxis\":{\"automargin\":true,\"gridcolor\":\"#EBF0F8\",\"linecolor\":\"#EBF0F8\",\"ticks\":\"\",\"title\":{\"standoff\":15},\"zerolinecolor\":\"#EBF0F8\",\"zerolinewidth\":2}}},\"xaxis\":{\"anchor\":\"y\",\"domain\":[0.0,0.44],\"title\":{\"text\":\"Study Time\"},\"tickmode\":\"array\",\"tickvals\":[1,2,3,4]},\"yaxis\":{\"anchor\":\"x\",\"domain\":[0.0,1.0],\"title\":{\"text\":\"Average Final Grade (G3)\"}},\"xaxis2\":{\"anchor\":\"y2\",\"domain\":[0.56,1.0],\"title\":{\"text\":\"Study Time\"},\"tickmode\":\"array\",\"tickvals\":[1,2,3,4]},\"yaxis2\":{\"anchor\":\"x2\",\"domain\":[0.0,1.0],\"title\":{\"text\":\"Average Final Grade (G3)\"}},\"annotations\":[{\"font\":{\"size\":16},\"showarrow\":false,\"text\":\"Math\",\"x\":0.22,\"xanchor\":\"center\",\"xref\":\"paper\",\"y\":1.0,\"yanchor\":\"bottom\",\"yref\":\"paper\"},{\"font\":{\"size\":16},\"showarrow\":false,\"text\":\"Portuguese\",\"x\":0.78,\"xanchor\":\"center\",\"xref\":\"paper\",\"y\":1.0,\"yanchor\":\"bottom\",\"yref\":\"paper\"}],\"legend\":{\"title\":{\"text\":\"Paid Extra Classes\"}},\"height\":450,\"width\":1000},                        {\"responsive\": true}                    ).then(function(){\n                            \nvar gd = document.getElementById('8a5a029a-c0ae-45df-800e-861dfc0d305b');\nvar x = new MutationObserver(function (mutations, observer) {{\n        var display = window.getComputedStyle(gd).display;\n        if (!display || display === 'none') {{\n            console.log([gd, 'removed!']);\n            Plotly.purge(gd);\n            observer.disconnect();\n        }}\n}});\n\n// Listen for the removal of the full notebook cells\nvar notebookContainer = gd.closest('#notebook-container');\nif (notebookContainer) {{\n    x.observe(notebookContainer, {childList: true});\n}}\n\n// Listen for the clearing of the current output cell\nvar outputEl = gd.closest('.output');\nif (outputEl) {{\n    x.observe(outputEl, {childList: true});\n}}\n\n                        })                };            </script>        </div>","content_type":"text/html"}}},"children":[],"key":"ckiTZJjtpE"}],"visibility":"show","key":"asf6Kd3SON"}],"class":"col-page-right","visibility":"show","key":"RUyh4L8ZeT"},{"type":"block","kind":"notebook-content","children":[{"type":"paragraph","position":{"start":{"line":1,"column":1},"end":{"line":1,"column":1}},"children":[{"type":"emphasis","position":{"start":{"line":1,"column":1},"end":{"line":1,"column":1}},"children":[{"type":"text","value":"Figure 3. Average Final Grade by Study Time and Paid Extra Classes","position":{"start":{"line":1,"column":1},"end":{"line":1,"column":1}},"key":"nNXEqOPS55"}],"key":"PxuWYCCYwM"}],"key":"CSDe6viCTd"}],"key":"u37SnnwMr2"},{"type":"block","kind":"notebook-content","children":[{"type":"paragraph","position":{"start":{"line":1,"column":1},"end":{"line":1,"column":1}},"children":[{"type":"text","value":"Figure 3 indicates that the relationship between extra classes and study time, and average of final grade differs between mathematics and Portuguese. For Mathematics, students who did not attend extra classes experienced a fluctuating pattern, whereas those attending extra classes showed a stable increase in study time with increased average grades. This is because extra classes or study time may not fully explain mathematical grades; their performance may also depend on math-solving tactics, learning strategies, and conceptual understanding (","position":{"start":{"line":1,"column":1},"end":{"line":1,"column":1}},"key":"UDfUtm0FxW"},{"type":"cite","url":"https://doi.org/10.14812/cuefd.1292823","position":{"start":{"line":1,"column":1},"end":{"line":1,"column":1}},"children":[{"type":"text","value":"Uyandıran & Tarım (2024)","key":"rgvZigRPC5"}],"kind":"narrative","label":"Uyand_ran_2024","identifier":"https://doi.org/10.14812/cuefd.1292823","enumerator":"5","key":"ecoHpqfURD"},{"type":"text","value":", ","position":{"start":{"line":1,"column":1},"end":{"line":1,"column":1}},"key":"kFVcgCg7Ad"},{"type":"cite","url":"https://doi.org/10.18009/jcer.844906","position":{"start":{"line":1,"column":1},"end":{"line":1,"column":1}},"children":[{"type":"text","value":"TURGUT (2021)","key":"KE5ueyM0GP"}],"kind":"narrative","label":"TURGUT_2021","identifier":"https://doi.org/10.18009/jcer.844906","enumerator":"6","key":"MgpBsyTAlL"},{"type":"text","value":"). For Portuguese, students studying more without extra classes tend to achieve higher grades than those who combine both of them, while the latter showed a fluctuating pattern. This difference lies in the subject characteristics: mathematics requires teacher’s problem-solving methods and guidance, as well as concentration and comprehension from students (","position":{"start":{"line":1,"column":1},"end":{"line":1,"column":1}},"key":"ujldVrAPOi"},{"type":"cite","url":"https://doi.org/10.12973/ejmste/79805","position":{"start":{"line":1,"column":1},"end":{"line":1,"column":1}},"children":[{"type":"text","value":"Alegre-Ansuategui ","key":"pYhTewrEkO"},{"type":"emphasis","children":[{"type":"text","value":"et al.","key":"lDrAyAYxtQ"}],"key":"ilY0Ko3Y2G"},{"type":"text","value":" (2017)","key":"J6VxReozvo"}],"kind":"narrative","label":"Alegre2017Peer","identifier":"https://doi.org/10.12973/ejmste/79805","enumerator":"7","key":"y3A4L2Zyi3"},{"type":"text","value":", ","position":{"start":{"line":1,"column":1},"end":{"line":1,"column":1}},"key":"wVd4AytT0E"},{"type":"cite","url":"https://doi.org/10.14812/cuefd.1292823","position":{"start":{"line":1,"column":1},"end":{"line":1,"column":1}},"children":[{"type":"text","value":"Uyandıran & Tarım (2024)","key":"vdX4VYKKdz"}],"kind":"narrative","label":"Uyand_ran_2024","identifier":"https://doi.org/10.14812/cuefd.1292823","enumerator":"5","key":"xjohn3caDv"},{"type":"text","value":"), while with foreign languages, self-study and practice in reality will be more effective in improving students’ language skills (","position":{"start":{"line":1,"column":1},"end":{"line":1,"column":1}},"key":"f86lE6zAG3"},{"type":"cite","url":"https://doi.org/10.1017/s0272263116000280","position":{"start":{"line":1,"column":1},"end":{"line":1,"column":1}},"children":[{"type":"text","value":"Nakata (2016)","key":"XnTgCYEWK5"}],"kind":"narrative","label":"Nakata_2016","identifier":"https://doi.org/10.1017/s0272263116000280","enumerator":"8","key":"PkCWuphlID"},{"type":"text","value":", ","position":{"start":{"line":1,"column":1},"end":{"line":1,"column":1}},"key":"L6fbbwTVgN"},{"type":"cite","url":"https://doi.org/10.1080/09588221.2022.2055081","position":{"start":{"line":1,"column":1},"end":{"line":1,"column":1}},"children":[{"type":"text","value":"Zhang & Zou (2022)","key":"FgPTutx7jC"}],"kind":"narrative","label":"Zhang_2022","identifier":"https://doi.org/10.1080/09588221.2022.2055081","enumerator":"9","key":"Xqi23sQuOu"},{"type":"text","value":").","position":{"start":{"line":1,"column":1},"end":{"line":1,"column":1}},"key":"buSKFjcyh3"}],"key":"iJZoQ63pL0"}],"key":"Q3OhiAgi5R"},{"type":"block","kind":"notebook-content","children":[{"type":"heading","depth":3,"position":{"start":{"line":1,"column":1},"end":{"line":1,"column":1}},"children":[{"type":"text","value":"Stress level","position":{"start":{"line":1,"column":1},"end":{"line":1,"column":1}},"key":"OUQ65QmvZ5"}],"identifier":"stress-level","label":"Stress level","html_id":"stress-level","implicit":true,"key":"MIoVqm1cKw"},{"type":"paragraph","position":{"start":{"line":3,"column":1},"end":{"line":3,"column":1}},"children":[{"type":"emphasis","position":{"start":{"line":3,"column":1},"end":{"line":3,"column":1}},"children":[{"type":"text","value":"Despite possibly affecting mental wellbeing, strictly follow intense study schedule brings fruitful result","position":{"start":{"line":3,"column":1},"end":{"line":3,"column":1}},"key":"ZzcrUzr0Lm"}],"key":"z42CeO0urD"}],"key":"Fcbqiw8HZl"}],"key":"ZWXFOKvYnC"},{"type":"block","kind":"notebook-code","data":{"editable":true,"slideshow":{"slide_type":""},"tags":[]},"children":[{"type":"code","lang":"python","executable":true,"value":"%run ../plots/pers1_subarg4.ipynb","visibility":"remove","key":"mcVZemd8Vo"},{"type":"outputs","id":"kFqOFka06YCiEJVmzzp6_","children":[{"type":"output","jupyter_data":{"output_type":"display_data","metadata":{},"data":{"text/html":{"content":"        <script>\n        window.PlotlyConfig = {MathJaxConfig: 'local'};\n        if (window.MathJax && window.MathJax.Hub && window.MathJax.Hub.Config) {window.MathJax.Hub.Config({SVG: {font: \"STIX-Web\"}});}\n        </script>\n        <script type=\"module\">import \"https://cdn.plot.ly/plotly-3.5.0.min\"</script>\n        ","content_type":"text/html"}}},"children":[],"key":"xYlsjYw1NG"},{"type":"output","jupyter_data":{"output_type":"display_data","metadata":{},"data":{"application/vnd.plotly.v1+json":{"content_type":"application/vnd.plotly.v1+json","hash":"79212f9cd7533b9481e8e71140405ece","path":"/79212f9cd7533b9481e8e71140405ece.json"},"image/png":{"content_type":"image/png","hash":"64dbbd3c506b7fe189615dff5866fb6d","path":"/64dbbd3c506b7fe189615dff5866fb6d.png"},"text/html":{"content_type":"text/html","hash":"bf6b2f8e0e615d7636a37c30abf61cc3","path":"/bf6b2f8e0e615d7636a37c30abf61cc3.html"}}},"children":[],"key":"Ppr09w74sC"}],"visibility":"show","key":"xXglprVPqV"}],"class":"col-page-right","visibility":"show","key":"PC9ctlkQNV"},{"type":"block","kind":"notebook-content","children":[{"type":"paragraph","position":{"start":{"line":1,"column":1},"end":{"line":1,"column":1}},"children":[{"type":"emphasis","position":{"start":{"line":1,"column":1},"end":{"line":1,"column":1}},"children":[{"type":"text","value":"Figure 4 Grade Distribution by Stress Level","position":{"start":{"line":1,"column":1},"end":{"line":1,"column":1}},"key":"pb4UbqhzvD"}],"key":"SeTVdhmovU"}],"key":"TLV2XfExqk"}],"key":"mGoguEXcnU"},{"type":"block","kind":"notebook-content","children":[{"type":"paragraph","position":{"start":{"line":1,"column":1},"end":{"line":1,"column":1}},"children":[{"type":"text","value":"Overall, data shows that high stress correlates with high grades. Since strict, intensive study schedules are a very plausible reason students report high stress (rather than e.g. financial stress or personal issues, given this is a student lifestyle dataset), this chart visually supports the idea that strict lifestyles pay off academically. This phenomenon can be explained by the concept of eustress, which is a type of positive stress that result in positive outcome, which stems from the Yerkes-Dodson Law stating that ‘‘increasing stress is beneficial to performance until some optimum level is reached…’’ (","position":{"start":{"line":1,"column":1},"end":{"line":1,"column":1}},"key":"QzEYZnsGjR"},{"type":"cite","url":"https://doi.org/10.1108/02683940310502412","position":{"start":{"line":1,"column":1},"end":{"line":1,"column":1}},"children":[{"type":"text","value":"Le Fevre ","key":"vMfXILq5SR"},{"type":"emphasis","children":[{"type":"text","value":"et al.","key":"wp8O7V37cQ"}],"key":"XiKhTH9GD9"},{"type":"text","value":" (2003)","key":"Nj9zZO2Zly"}],"kind":"narrative","label":"Le_Fevre_2003","identifier":"https://doi.org/10.1108/02683940310502412","enumerator":"10","key":"VS5GuEnzBM"},{"type":"text","value":") However, it is worth noting that grades spread quite widely in the high stress group, which is shown more clearly in the with-datapoints version, thus the pattern may not apply universally every time.","position":{"start":{"line":1,"column":1},"end":{"line":1,"column":1}},"key":"rIvBMLRL1x"}],"key":"bhApJZ0xia"}],"key":"HUWDpxvRLo"}],"key":"H9Mr5ZSKn9"},"references":{"cite":{"order":["Foster_2023","Zhang_2020","Ros_rio_2012","Cred__2010","Uyand_ran_2024","TURGUT_2021","Alegre2017Peer","Nakata_2016","Zhang_2022","Le_Fevre_2003"],"data":{"Foster_2023":{"label":"Foster_2023","enumerator":"1","doi":"10.1002/curj.213","html":"Foster, C. (2023). Problem solving in the mathematics curriculum: From domain‐general strategies to domain‐specific tactics. <i>The Curriculum Journal</i>, <i>34</i>(4), 594–612. <a target=\"_blank\" rel=\"noreferrer\" href=\"https://doi.org/10.1002/curj.213\">10.1002/curj.213</a>","url":"https://doi.org/10.1002/curj.213"},"Zhang_2020":{"label":"Zhang_2020","enumerator":"2","doi":"10.1080/09588221.2020.1744666","html":"Zhang, R., & Zou, D. (2020). Types, purposes, and effectiveness of state-of-the-art technologies for second and foreign language learning. <i>Computer Assisted Language Learning</i>, <i>35</i>(4), 696–742. <a target=\"_blank\" rel=\"noreferrer\" href=\"https://doi.org/10.1080/09588221.2020.1744666\">10.1080/09588221.2020.1744666</a>","url":"https://doi.org/10.1080/09588221.2020.1744666"},"Ros_rio_2012":{"label":"Ros_rio_2012","enumerator":"3","doi":"10.1007/s10212-012-0167-9","html":"Rosário, P., Núñez, J. C., Valle, A., González-Pienda, J., & Lourenço, A. (2012). Grade level, study time, and grade retention and their effects on motivation, self-regulated learning strategies, and mathematics achievement: a structural equation model. <i>European Journal of Psychology of Education</i>, <i>28</i>(4), 1311–1331. <a target=\"_blank\" rel=\"noreferrer\" href=\"https://doi.org/10.1007/s10212-012-0167-9\">10.1007/s10212-012-0167-9</a>","url":"https://doi.org/10.1007/s10212-012-0167-9"},"Cred__2010":{"label":"Cred__2010","enumerator":"4","doi":"10.3102/0034654310362998","html":"Credé, M., Roch, S. G., & Kieszczynka, U. M. (2010). Class Attendance in College: A Meta-Analytic Review of the Relationship of Class Attendance With Grades and Student Characteristics. <i>Review of Educational Research</i>, <i>80</i>(2), 272–295. <a target=\"_blank\" rel=\"noreferrer\" href=\"https://doi.org/10.3102/0034654310362998\">10.3102/0034654310362998</a>","url":"https://doi.org/10.3102/0034654310362998"},"Uyand_ran_2024":{"label":"Uyand_ran_2024","enumerator":"5","doi":"10.14812/cuefd.1292823","html":"Uyandıran, A., & Tarım, K. (2024). The Effect of Student-Centered Strategies, Methods and Techniques Used in Mathematics Teaching on Problem Solving Skills: A Meta-Analysis Study. <i>Cukurova University Faculty of Education Journal</i>, <i>53</i>(1), 131–166. <a target=\"_blank\" rel=\"noreferrer\" href=\"https://doi.org/10.14812/cuefd.1292823\">10.14812/cuefd.1292823</a>","url":"https://doi.org/10.14812/cuefd.1292823"},"TURGUT_2021":{"label":"TURGUT_2021","enumerator":"6","doi":"10.18009/jcer.844906","html":"TURGUT, S. (2021). A Meta-Analysis of the Effects of Realistic Mathematics Education-based Teaching on Mathematical Achievement of Students in Turkey. <i>Journal of Computer and Education Research</i>, <i>9</i>(17), 300–326. <a target=\"_blank\" rel=\"noreferrer\" href=\"https://doi.org/10.18009/jcer.844906\">10.18009/jcer.844906</a>","url":"https://doi.org/10.18009/jcer.844906"},"Alegre2017Peer":{"label":"Alegre2017Peer","enumerator":"7","doi":"10.12973/ejmste/79805","html":"Alegre-Ansuategui, F. J., Moliner, L., Lorenzo, G., & Maroto, A. (2017). Peer Tutoring and Academic Achievement in Mathematics: A Meta-Analysis. <i>EURASIA Journal of Mathematics, Science and Technology Education</i>, <i>14</i>(1). <a target=\"_blank\" rel=\"noreferrer\" href=\"https://doi.org/10.12973/ejmste/79805\">10.12973/ejmste/79805</a>","url":"https://doi.org/10.12973/ejmste/79805"},"Nakata_2016":{"label":"Nakata_2016","enumerator":"8","doi":"10.1017/s0272263116000280","html":"Nakata, T. (2016). DOES REPEATED PRACTICE MAKE PERFECT? THE EFFECTS OF WITHIN-SESSION REPEATED RETRIEVAL ON SECOND LANGUAGE VOCABULARY LEARNING. <i>Studies in Second Language Acquisition</i>, <i>39</i>(4), 653–679. <a target=\"_blank\" rel=\"noreferrer\" href=\"https://doi.org/10.1017/s0272263116000280\">10.1017/s0272263116000280</a>","url":"https://doi.org/10.1017/s0272263116000280"},"Zhang_2022":{"label":"Zhang_2022","enumerator":"9","doi":"10.1080/09588221.2022.2055081","html":"Zhang, R., & Zou, D. (2022). Self-regulated second language learning: a review of types and benefits of strategies, modes of teacher support, and pedagogical implications. <i>Computer Assisted Language Learning</i>, <i>37</i>(4), 720–765. <a target=\"_blank\" rel=\"noreferrer\" href=\"https://doi.org/10.1080/09588221.2022.2055081\">10.1080/09588221.2022.2055081</a>","url":"https://doi.org/10.1080/09588221.2022.2055081"},"Le_Fevre_2003":{"label":"Le_Fevre_2003","enumerator":"10","doi":"10.1108/02683940310502412","html":"Le Fevre, M., Matheny, J., & Kolt, G. S. (2003). Eustress, distress, and interpretation in occupational stress. <i>Journal of Managerial Psychology</i>, <i>18</i>(7), 726–744. <a target=\"_blank\" rel=\"noreferrer\" href=\"https://doi.org/10.1108/02683940310502412\">10.1108/02683940310502412</a>","url":"https://doi.org/10.1108/02683940310502412"}}}}}